Workbook

Sheet CNAE
A1: Empreses actives
A2: Resultats per comunitats autònomes
A4: Empreses per CCAA, activitat principal (grups CNAE 2009) i estrat d'assalariats (antiga estratificació).
A5: Unitats: Empreses
B7: Total | C7: Porcentaje | D7: Total PYMES CAT | E7: Sin asalariados | F7: De 1 a 2 | G7: De 3 a 5 | H7: De 6 a 9 | I7: De 10 a 19 | J7: De 20 a 49 | K7: De 50 a 99 | L7: De 100 a 199
B8: 2020 | C8: 2020 | D8: 2020 | E8: 2020 | F8: 2020 | G8: 2020 | H8: 2020 | I8: 2020 | J8: 2020 | K8: 2020 | L8: 2020
A9: Total Nacional
A10: Total CNAE | B10: 3404428 | E10: 1912010 | F10: 907192 | G10: 305986 | H10: 125472 | I10: 81298 | J10: 46101 | K10: 13275 | L10: 6906
A11: 05 Extracción de antracita, hulla y lignito | B11: 58 | E11: 43 | F11: 5 | G11: 1 | H11: 2 | I11: 3 | J11: 0 | K11: 3 | L11: 0
A12: 051 Extracción de antracita y hulla | B12: 55 | E12: 41 | F12: 4 | G12: 1 | H12: 2 | I12: 3 | J12: 0 | K12: 3 | L12: 0
A13: 052 Extracción de lignito | B13: 3 | E13: 2 | F13: 1 | G13: 0 | H13: 0 | I13: 0 | J13: 0 | K13: 0 | L13: 0
A14: 06 Extracción de crudo de petróleo y gas natural | B14: 8 | E14: 2 | F14: 4 | G14: 1 | H14: 0 | I14: 0 | J14: 1 | K14: 0 | L14: 0
A15: 061 Extracción de crudo de petróleo | B15: 6 | E15: 1 | F15: 4 | G15: 1 | H15: 0 | I15: 0 | J15: 0 | K15: 0 | L15: 0
A16: 062 Extracción de gas natural | B16: 2 | E16: 1 | F16: 0 | G16: 0 | H16: 0 | I16: 0 | J16: 1 | K16: 0 | L16: 0
A17: 07 Extracción de minerales metálicos | B17: 68 | E17: 34 | F17: 12 | G17: 6 | H17: 2 | I17: 4 | J17: 2 | K17: 4 | L17: 0
A18: 071 Extracción de minerales de hierro | B18: 19 | E18: 11 | F18: 3 | G18: 3 | H18: 1 | I18: 0 | J18: 1 | K18: 0 | L18: 0
A19: 072 Extracción de minerales metálicos no férreos | B19: 49 | E19: 23 | F19: 9 | G19: 3 | H19: 1 | I19: 4 | J19: 1 | K19: 4 | L19: 0
A20: 08 Otras industrias extractivas | B20: 1768 | E20: 556 | F20: 427 | G20: 244 | H20: 181 | I20: 207 | J20: 120 | K20: 25 | L20: 4
A21: 081 Extracción de piedra, arena y arcilla | B21: 1607 | E21: 499 | F21: 389 | G21: 226 | H21: 167 | I21: 193 | J21: 111 | K21: 19 | L21: 3
... A343: 960 Otros servicios personales | B343: 137801 | E343: 75338 | F343: 47259 | G343: 10548 | H343: 3297 | I343: 830 | J343: 377 | K343: 94 | L343: 30
A344: 09 Cataluña
A345: Total CNAE | B345: 629876 | C345: =D345/$D$345 -> 1 | D345: =SUM(E345:L345) -> 628520 | E345: 365634 | F345: 158687 | G345: 53214 | H345: 22558 | I345: 15229 | J345: 8947 | K345: 2774 | L345: 1477
A346: 05 Extracción de antracita, hulla y lignito | B346: 5 | C346: =D346/$D$345 -> 7.9551963e-06 | D346: =SUM(E346:L346) -> 5 | E346: 5 | F346: 0 | G346: 0 | H346: 0 | I346: 0 | J346: 0 | K346: 0 | L346: 0
A347: 051 Extracción de antracita y hulla | B347: 5 | C347: =D347/$D$345 -> 7.9551963e-06 | D347: =SUM(E347:L347) -> 5 | E347: 5 | F347: 0 | G347: 0 | H347: 0 | I347: 0 | J347: 0 | K347: 0 | L347: 0
A348: 052 Extracción de lignito | B348: 0 | C348: =D348/$D$345 -> 0 | D348: =SUM(E348:L348) -> 0 | E348: 0 | F348: 0 | G348: 0 | H348: 0 | I348: 0 | J348: 0 | K348: 0 | L348: 0
A349: 06 Extracción de crudo de petróleo y gas natural | B349: 0 | C349: =D349/$D$345 -> 0 | D349: =SUM(E349:L349) -> 0 | E349: 0 | F349: 0 | G349: 0 | H349: 0 | I349: 0 | J349: 0 | K349: 0 | L349: 0
A350: 061 Extracción de crudo de petróleo | B350: 0 | C350: =D350/$D$345 -> 0 | D350: =SUM(E350:L350) -> 0 | E350: 0 | F350: 0 | G350: 0 | H350: 0 | I350: 0 | J350: 0 | K350: 0 | L350: 0
A351: 062 Extracción de gas natural | B351: 0 | C351: =D351/$D$345 -> 0 | D351: =SUM(E351:L351) -> 0 | E351: 0 | F351: 0 | G351: 0 | H351: 0 | I351: 0 | J351: 0 | K351: 0 | L351: 0
A352: 07 Extracción de minerales metálicos | B352: 2 | C352: =D352/$D$345 -> 3.1820785e-06 | D352: =SUM(E352:L352) -> 2 | E352: 0 | F352: 1 | G352: 1 | H352: 0 | I352: 0 | J352: 0 | K352: 0 | L352: 0
A353: 071 Extracción de minerales de hierro | B353: 1 | C353: =D353/$D$345 -> 1.5910393e-06 | D353: =SUM(E353:L353) -> 1 | E353: 0 | F353: 1 | G353: 0 | H353: 0 | I353: 0 | J353: 0 | K353: 0 | L353: 0
A354: 072 Extracción de minerales metálicos no férreos | B354: 1 | C354: =D354/$D$345 -> 1.5910393e-06 | D354: =SUM(E354:L354) -> 1 | E354: 0 | F354: 0 | G354: 1 | H354: 0 | I354: 0 | J354: 0 | K354: 0 | L354: 0
A355: 08 Otras industrias extractivas | B355: 154 | C355: =D355/$D$345 -> 0.00024183797 | D355: =SUM(E355:L355) -> 152 | E355: 53 | F355: 31 | G355: 19 | H355: 8 | I355: 27 | J355: 11 | K355: 3 | L355: 0
A356: 081 Extracción de piedra, arena y arcilla | B356: 141 | C356: =D356/$D$345 -> 0.00022433654 | D356: =SUM(E356:L356) -> 141 | E356: 49 | F356: 29 | G356: 19 | H356: 8 | I356: 23 | J356: 11 | K356: 2 | L356: 0
... A678: 960 Otros servicios personales | B678: 23510 | C678: =D678/$D$345 -> 0.037395787 | D678: =SUM(E678:L678) -> 23504 | E678: 12316 | F678: 8516 | G678: 1823 | H678: 597 | I678: 144 | J678: 76 | K678: 20 | L678: 12
A681: Notas:
A683: Fuente:

Sheet Crèdits
A1: Crèdits © Generalitat de Catalunya Departament d’Acció Climàtica, Alimentació i Agenda Rural Primera edició, gener de 2024 AUTORS Ramon Scholl1, Oliver Canosa Daroca1, Oriol Lafarga Amorós1, Eduardo Macon Bayarri1, Clara Sánchez Cerdà1 COORDINACIÓ Maria José Sarrias Galcerán2, Virginia Ferrer-Vidal Cortella2 1 TECNOAMBIENTE 2 Direcció general de Canvi Climàtic i Qualitat Ambiental Departament d’Acció Climàtica, Alimentació i Agenda Rural

Sheet Mapa de materialitat
B2: Mapa de materialitat Ambiental, Social i de Governança (ASG) per a la PIME per sector econòmic | N2: Medi ambient | O2: Eficiència energètica i energies renovables | P2: Emissions de GEH | Q2: Impactes físics del canvi climàtic | R2: Gestió sostenible de l'aigua | S2: Gestió de residus i materials perillosos | T2: Biodiversitat i ecosistemes | U2: Disseny del producte i gestió del cicle de vida | V2: Oportunitats de tecnologies/aplicacions sostenibles | W2: Subministrament de matèries primeres / productes venuts | X2: Qualitat de l'aire | Y2: Seguretat química | Z2: Materials d'embalatge | AA2: Social | AB2: Seguretat i salut laboral | AC2: Desenvolupament del capital humà | AD2: Ciberseguretat | AE2: Protecció de dades | AF2: Seguretat i qualitat del producte | AG2: Benestar del client | AH2: Condicions laborals | AI2: Pràctiques de venda i etiquetatge | AJ2: Compromís dels empleats, diversitat i inclusió | AK2: Oportunitats de nutrició i salut | AL2: Estàndards laborals en la cadena de valor | AM2: Assequibilitat i accés als serveis | AN2: Relacions amb les comunitats afectades | AO2: Governança | AP2: Bon govern | AQ2: Competència responsable | AR2: Gestió de riscos d'incidents crítics | AS2: Gestió de riscos sistèmics | AT2: Gestió de la cadena de subministrament | AU2: Resiliència del model de negoci
C3: Total | D3: Porcentaje | E3: Total PIMES CAT | F3: Sin asalariados | G3: De 1 a 2 | H3: De 3 a 5 | I3: De 6 a 9 | J3: De 10 a 19 | K3: De 20 a 49 | L3: De 50 a 99 | M3: De 100 a 199
B4: Indústria alimentària i de begudes | D4: 0.006 | E4: 3750
B5: Indústria de la moda i tèxtil | D5: 0.0067 | E5: 4225
B6: Indústria de fusta i paper | D6: 0.0034 | E6: 2138
B7: Altres indústries manufactureres | D7: 0.025 | E7: 15698
B8: Indústries de serveis d'aigua i tractament de residus | D8: 0.0014 | E8: 894
B9: Construcció | C9: 40714 | D9: =E9/#REF! -> #REF! | E9: =SUM(F9:M9) -> 40705 | F9: 26920 | G9: 8810 | H9: 2711 | I9: 1135 | J9: 725 | K9: 321 | L9: 67 | M9: 16
B10: Serveis especialistes de construcció | C10: 33298 | D10: =E10/#REF! -> #REF! | E10: =SUM(F10:M10) -> 33287 | F10: 18164 | G10: 9181 | H10: 2998 | I10: 1330 | J10: 985 | K10: 503 | L10: 97 | M10: 29
B11: Serveis tècnics d'arquitectura i enginyeria; assaigs i anàlisis tècniques | C11: 21224 | D11: =E11/#REF! -> #REF! | E11: =SUM(F11:M11) -> 21207 | F11: 15419 | G11: 4021 | H11: 874 | I11: 395 | J11: 336 | K11: 109 | L11: 37 | M11: 16
B12: Venda i reparació de vehicles de motor i motocicletes | C12: 10707 | D12: =E12/#REF! -> #REF! | E12: =SUM(F12:M12) -> 10690 | F12: 4440 | G12: 3957 | H12: 1260 | I12: 459 | J12: 335 | K12: 157 | L12: 44 | M12: 38
B13: Comerç a l'engròs i intermediaris del comerç, excepte de vehicles de motor i motocicletes | C13: 41693 | D13: =E13/#REF! -> #REF! | E13: =SUM(F13:M13) -> 41591 | F13: 21277 | G13: 11024 | H13: 3710 | I13: 2561 | J13: 1514 | K13: 1006 | L13: 346 | M13: 153
B14: Comerç al detall, excepte de vehicles de motor i motocicletes | C14: 69185 | D14: =E14/#REF! -> #REF! | E14: =SUM(F14:M14) -> 69116 | F14: 31160 | G14: 25048 | H14: 9314 | I14: 2241 | J14: 759 | K14: 438 | L14: 103 | M14: 53
B15: Transport terrestre | C15: 33561 | D15: =E15/#REF! -> #REF! | E15: =SUM(F15:M15) -> 33529 | F15: 23147 | G15: 7221 | H15: 1542 | I15: 721 | J15: 493 | K15: 316 | L15: 60 | M15: 29
B16: Serveis d'allotjaments i serveis de menjars i begudes (hoteleria) | C16: 40509 | D16: =E16/#REF! -> #REF! | E16: =SUM(F16:M16) -> 40468 | F16: 12343 | G16: 15829 | H16: 8212 | I16: 2365 | J16: 1023 | K16: 534 | L16: 108 | M16: 54
B17: Programació, consultoria i altres activitats relacionades amb la informàtica | C17: 9320 | D17: =E17/#REF! -> #REF! | E17: =SUM(F17:M17) -> 9290 | F17: 5921 | G17: 1850 | H17: 554 | I17: 326 | J17: 339 | K17: 199 | L17: 59 | M17: 42
B18: Activitats auxiliars als serveis financers i les assegurances | C18: 12372 | D18: =E18/#REF! -> #REF! | E18: =SUM(F18:M18) -> 12369 | F18: 9464 | G18: 2326 | H18: 391 | I18: 96 | J18: 46 | K18: 30 | L18: 11 | M18: 5
B19: Activitats jurídiques i de comptabilitat | C19: 25592 | D19: =E19/#REF! -> #REF! | E19: =SUM(F19:M19) -> 25578 | F19: 15593 | G19: 6597 | H19: 1866 | I19: 809 | J19: 579 | K19: 108 | L19: 21 | M19: 5
B20: Activitats de les seus centrals; activitats de consultoria de gestió empresarial | C20: 4762 | D20: =E20/#REF! -> #REF! | E20: =SUM(F20:M20) -> 4741 | F20: 1975 | G20: 1725 | H20: 485 | I20: 247 | J20: 178 | K20: 83 | L20: 33 | M20: 15
... B27: Activitats sanitàries | C27: 33537 | D27: =E27/#REF! -> #REF! | E27: =SUM(F27:M27) -> 33455 | F27: 25363 | G27: 5289 | H27: 1610 | I27: 592 | J27: 339 | K27: 159 | L27: 69 | M27: 34

Sheet AUTO
B1: Mediambiental | C1: Eficiència energètica i energies renovables | D1: Emissions de GEH | E1: Impactes físics del canvi climàtic | F1: Gestió sostenible de l'aigua | G1: Gestió de residus i materials perillosos | H1: Biodiversitat i ecosistemes | I1: Disseny del producte i gestió del cicle de vida | J1: Oportunitats de tecnologies / aplicacions sostenibles | K1: Subministrament de matèries primeres / productes venuts | L1: Qualitat de l'aire | M1: Seguretat química | N1: Materials d'embalatge | O1: Oportunitats de construcció sostenible | P1: Social | Q1: Salut i seguretat laboral | R1: Desenvolupament del capital humà | S1: Ciberseguretat | T1: Protecció de dades | U1: Seguretat i qualitat del producte | V1: Benestar del client | W1: Condicions laborals | X1: Practiques de venda i etiquetatge | Y1: Compromís dels empleats, diversitat i inclusió | Z1: Oportunitats de nutrició i salut | AA1: Estàndards de treball en la cadena de valor | AB1: Accés i assequibilitat | AC1: Relacions amb les comunitats afectades | AD1: Governança | AE1: Bon govern | AF1: Competència responsable | AG1: Gestió de riscos d'incidents critics | AH1: Gestió de riscos sistèmics | AI1: Gestió de la cadena de subministrament | AJ1: Resiliència del model de negoci
B2: Descripció | C2: L'eficiència energètica i les energies renovables se centren a disminuir el consum energètic respecte de la producció. Les empreses amb una alta eficiència energètica són més sostenibles ambientalment i econòmicament, ja que requereixen menys recursos (combustibles, electricitat, matèries primeres, etc.) per generar el mateix volum d'ingressos que una de menys eficient. | D2: Les emissions de gasos amb efecte d'hivernacle i les energies renovables són categories estretament vinculades amb el canvi climàtic. Les empreses amb una major petjada de carboni contribueixen en major mesura al canvi climàtic. Reduir els impactes relacionats amb aquest tema requereix una reducció de la petjada de carboni de l'empresa. Això requereix una transició envers fonts d'energia renovables i la implementació d'estratègies per assolir emissions netes zero. | E2: Els impactes físics del canvi climàtic són aquells que experimenta, experimentarà o ja ha experimentat l'empresa vinculats a modificacions en variables climàtiques. Per exemple, la manca d'aigua a causa d'una sequera prolongada, danys provocats per inundacions causades per una tempesta especialment forta, pedregades o els costos en què l'empresa ha d'incórrer per adaptar-se a un clima canviant. | F2: La gestió sostenible de l'aigua tracta d'assegurar que el consum i ús d'aquesta aigua per part de l'empresa estiguin alineats amb la capacitat de recuperar-se de l'ecosistema i no generin impactes negatius. Les necessitats de consumir aigua estan lligades al sector i a la ubicació de la planta. És important destacar que les empreses amb operacions en zones amb estrès hídric caldrà que avaluïn com fer una gestió sostenible dels recursos hídrics. Això inclou reduir el consum d'aigua, millorar la captura i reutilització de les aigües grises i millorar el tractament d'aigües residuals, entre d'altres. | G2: La gestió de residus perillosos i no perillosos és un àmbit en constant evolució normativa. L'adequada gestió de residus i materials perillosos és clau per reduir la contaminació causada per l'empresa o els productes que posa al mercat. Optimitzar el disseny i la producció i treballar paral·lelament a millorar la gestió de residus és clau per transicionar envers una economia circular que redueixi la necessitat d'explotació de nous recursos naturals. Per tant, les empreses que gestionen els seus residus i eviten la seva generació són més sostenibles i estan més alineades amb els principis de l'economia circular. | H2: Aquesta categoria se centra en els impactes de les operacions o els actius d'una empresa sobre ecosistemes i la seva biodiversitat. Les activitats amb potencials impactes significatius són aquelles vinculades amb canvis en l'ús del sòl per a exploració/explotació de recursos naturals, construcció, agricultura extensiva, etc. Els impactes poden produir pèrdua de biodiversitat, destrucció d'hàbitats, deforestació i pèrdua de serveis ecosistèmics bàsics. Les empreses haurien d'avaluar les seves dependències i impactes sobre el capital natural (natura), mitigar els riscos associats i fomentar un impacte positiu en totes les fases de la cadena de valor de l'empresa. | I2: El disseny dels productes i els seus cicles de vida són molt importants per gestionar l'impacte mediambiental de l'empresa. L'ecodisseny pot facilitar la reparació i el manteniment del producte i millorar-ne la tria dels materials més adequats i la reuitilització. Un correcte ecodisseny assegura una reducció dels impactes en tot el cicle de vida del producte. Les empreses que tenen en compte els impactes durant tot el cicle de vida permeten reduir l'impacte total del producte o servei en l'ús de materials, disseny industrial, producció i gestió de residus. D'aquesta manera, les empreses s'adapten als esquemes de responsabilitat ampliada del productor o futures normatives enfocades a la circularitat de l'economia. | J2: Les oportunitats de tecnologies/aplicacions sostenibles són rellevants en aquells sectors on hi ha tecnologies descarbonitzades que poden ajudar l'empresa a assolir els seus objectius de reducció d'emissons. Per exemple, la instal·lació de renovables en el sector d'energia o les aplicacions de tecnologies verdes a la construcció de nous edificis per al sector de l'edificació són oportunitats importants per diferenciar-se de la competència en termes de sostenibilitat. La sostenibilitat planteja moltes oportunitats que asseguren una reducció de les despeses de l'empresa a llarg termini. | K2: El subministrament de matèries primeres és un tema crucial per a la sostenibilitat d'aquells sectors molt intensius en materials. Aquí les empreses haurien d'avaluar oportunitats per a una adquisició de matèries de manera sostenible amb proveïdors confiables i certificats i estratègies de recuperació de material que es pugui recuperar com a matèria primera. Aquest tema pot ser important tant per a empreses que adquireixen matèries primeres com per a empreses que adquireixen prefabricats o productes. Un exemple és la cadena de subministrament d'empreses alimentàries, on és obligatori poder demostrar que el producte utilitzat no prové de zones amb alta deforestació. | L2: Les emissions de contaminants com el diòxid de sofre (SOx), el diòxid de nitrogen (NOx) i els Compostos Orgànics Volàtils (VOC), entre d'altres, poden tenir un impacte significatiu sobre la qualitat de l'aire. Una mala qualitat de l'aire pot tenir efectes negatius tant sobre el medi ambient com sobre la salut de les comunitats afectades. Per tant, les empreses que duen a terme operacions que produeixen emissions a l'aire han d'avaluar el seu impacte sobre la qualitat de l'aire mitjançant controls regulars duts a terme per l'autoritat ambiental competent. Les empreses podrien considerar la instal·lació de filtres i altres mesures destinades a reduir les emissions de contaminants atmosfèrics. | M2: Garantir la seguretat química és de gran importància per preservar els ecosistemes i protegir les comunitats properes a instal·lacions que empren substàncies químiques perilloses. Les empreses que comercialitzen productes que contenen substàncies químiques perilloses susceptibles d'entrar en contacte amb l'entorn natural o els usuaris d'aquests productes és essencial que prenguin totes les mesures necessàries per prevenir aquesta situació. Millorar la seguretat química pot implicar la recerca d'alternatives de materials per a l'ús en els seus productes, dissenyar productes de manera segura per prevenir fuites de substàncies i elaborar un pla de gestió de residus al final del cicle de vida del producte. | N2: Els materials d'embalatge son part del dia a dia i en certs casos acaben a la natura. És important que el productor faci un exercici d'ecodisseny que asseguri el mínim ús de material i la màxima reciclabilitat. | O2: Les oportunitats de tecnologies/aplicacions sostenibles són rellevants per als sectors on hi ha tecnologies verdes o aplicacions sostenibles que es podrien implementar per afavorir la sostenibilitat de l'empresa. Per exemple, la instal·lació de capacitat de renovables en el sector de l'energia o les aplicacions de tecnologies verdes en la construcció de nous edificis per al sector de l'edificació són oportunitats importants per diferenciar-se de la competència en termes de sostenibilitat. | Q2: La salut i seguretat laboral hauria de ser una prioritat fonamental en qualsevol empresa. Totes les empreses han d'assegurar-se de proporcionar un entorn de treball segur i saludable per als seus empleats. Això és especialment crucial en aquelles empreses que duen a terme operacions perilloses o tenen el potencial d'afectar adversament la salut dels seus treballadors. Una de les mesures clau per assegurar la salut i seguretat dels empleats és designar un/a responsable de salut i seguretat la funció principal del qual consisteix a avaluar els riscos per als empleats i implementar mesures de mitigació corresponents. | R2: El desenvolupament del capital humà pot ser un factor important per a empreses en sectors que requereixen coneixements o habilitats específiques. Les empreses que no inverteixen en el desenvolupament dels seus empleats poden perdre competitivitat en el mercat laboral, la qual cosa pot afectar la seva capacitat d'atreure i mantenir personal capacitat. Per assegurar la sostenibilitat social i econòmica en el futur, l'empresa pot oferir oportunitats de creixement al seu personal. En la mateixa línia, per mantenir una posició competitiva al mercat, les empreses han d'invertir en la formació i educació dels seus empleats. | S2: La ciberseguretat tracta sobre la seguretat dels sistemes informàtics de les empreses. Aquests sistemes poden contenir informació crucial per a les operacions de l'empresa i/o dels seus clients, per la qual cosa és important comptar amb un bon nivell de protecció. Les empreses poden millorar la seva seguretat si assignen un responsable de ciberseguretat al departament d'IT. Addicionalment, podrien dur a terme proves de seguretat periòdiques i establir protocols per contenir qualsevol risc digital, entre d'altres. | T2: La protecció de dades se centra en l'emmagatzematge i la gestió segura de les dades de clients, empleats i altres grups d'interès. És important respectar el RGPD (UE 2016/679) que estableix els requisits de la protecció de dades a la UE. A més, és important que només persones assignades tinguin accés a les dades emmagatzemades per l'empresa i sempre respectant-ne la privacitat. Per assegurar la protecció, les empreses poden establir una política de protecció de dades, assignar una persona reponsable i assegurar que els sistemes informàtics són adequats per protegir-los. | U2: La seguretat i qualitat són aspectes importants del producte, no només des d'una perspectiva econòmica, sinó també des d'una perspectiva de sostenibilitat. Falles de seguretat i/o qualitat del producte poden afectar negativament la salut o la seguretat dels usuaris, la qual cosa pot produir una varietat de riscos tant per a la reputació de l'empresa com legals. Algunes de les mesures que les empreses poden prendre per gestionar aquests riscos són dur a terme proves de productes i gestionar el contingut, els ingredients i els químics utilitzats en el producte. | V2: Alguns productes poden tenir un impacte sobre el benestar a llarg termini dels clients. Això no es refereix a riscos de seguretat immediats, sinó a efectes que es desenvolupen amb el temps. Exemples d'aquests tipus d'impacte inclouen l'ús d'antibiòtics en la producció de carn, efectes negatius sobre la salut causats per aliments amb alt contingut de sal, sucre i greix i l'ús de substàncies que poden tenir efectes perjudicials després de llargs períodes d'exposició. Algunes mesures per protegir el benestar dels clients inclouen la implementació de mètodes de producció segurs i l'adaptació de receptes de productes per reduir la quantitat d'ingredients perjudicials. | W2: Per tenir una bona consideració social i contribuir a una societat més justa, les empreses haurien d'oferir bones condicions laborals als seus empleats. Això no es limita al compliment dels drets humans; també inclou drets laborals, remuneració justa, horaris dignes, pagament d'hores extres, etc. Addicionalment, per anar més enllà dels compliments legals, les empreses poden oferir oportunitats de creixement, dret a desconnexió digital, posicions híbrides o en remot i altres mesures de conciliació per promoure l'equilibri entre la vida laboral i la personal. | X2: És essencial mantenir Bones Pràctiques en la venda i l'etiquetatge de productes per prevenir qualsevol pràctica enganyosa. Les pràctiques enganyoses poden portar els consumidors a triar un producte que no s'ajusti a les seves necessitats o requeriments. Per tant, per garantir Bones Pràctiques en la venda i l'etiquetatge, una empresa ha de gestionar la transparència de la informació relacionada amb els seus productes, operacions i cadenes de valor. A més, és fonamental proporcionar informació precisa i rellevant sobre els productes, sense ocultar desavantatges o altres tipus d'informació d'interès. | Y2: El compromís dels empleats i la promoció de la diversitat i inclusió a l'empresa són temes socials de gran rellevància. Aquests aspectes asseguren que la força laboral sigui diversa i que s'ofereixin oportunitats sense discriminació, la qual cosa permet la inclusió de membres de les comunitats locals i els consumidors dels productes de l'empresa. Per fomentar el compromís, la diversitat i la inclusió en l'empresa, és fonamental establir polítiques antidiscriminatòries en el procés de reclutament i promoure una cultura corporativa inclusiva. | Z2: Particularment en la indústria alimentària i de begudes, les oportunitats relacionades amb la nutrició i la salut són fonamentals per proporcionar productes de més qualitat als consumidors. Des d'una perspectiva de sostenibilitat social, és crucial que les empreses aprofitin les oportunitats per oferir productes amb un major valor nutricional i beneficis per a la salut dels consumidors. Aquelles empreses que aprofiten aquestes oportunitats poden destacar en el mercat, la qual cosa al seu torn contribueix a la seva sostenibilitat econòmica. | AA2: És crucial mantenir alts estàndards laborals i condicions de treball dignes per a tots els empleats en la cadena de valor. L'empresa s'ha d'assegurar que tots els seus proveïdors respectin els drets laborals i humans, la qual cosa inclou garantir una remuneració justa, horaris laborals adequats i la prohibició del treball forçós i el treball infantil. Per assegurar condicions laborals acceptables en tota la cadena de valor, l'empresa pot requerir el compliment d'un codi de conducta per part dels seus proveïdors i dur a terme auditories en alguns d'ells per verificar-ne el compliment. | AB2: L'accés i l'assequibilitat, especialment de productes i serveis bàsics, és important per a la igualtat d'oportunitats. Les empreses haurien de gestionar els preus i costos de manera responsable per oferir els productes i serveis (bàsics) a un preu assequible per a totes les persones que ho necessitin. Addicionalment, s'hauria d'avaluar l'accessibilitat de productes, serveis i edificis a totes les persones, incloent-hi les persones amb discapacitat, i prendre mesures per assegurar l'accessibilitat universal. | AC2: Les organitzacions tenen un impacte sobre les comunitats on operen, tant a través d'impactes físics com a través de la interacció amb els membres d'aquestes comunitats que treballen a l'empresa. Per tant, és fonamental establir relacions sòlides i respectuoses envers les comunitats afectades a través d'un diàleg que permeti comprendre i abordar els impactes negatius generats per les operacions. Algunes eines que es poden utilitzar per mantenir relacions efectives amb les comunitats inclouen la realització de reunions periòdiques amb representants de la comunitat, la incorporació de membres de la societat a l'empresa i el manteniment d'una comunicació constant amb organitzacions locals. | AE2: El bon govern és un tema ampli, enfocat en la gestió responsable i ètica de l'organització en general. L'acompliment de bon govern està vinculat als codis ètics de l'empresa, l'estructura de la propietat i el control de l'empresa, la junta directiva (i la seva remuneració), una comptabilitat transparent, la política fiscal i la transparència. | AF2: La competència responsable és crucial per combatre els monopolis i el lobbisme en les indústries. El seu objectiu principal és prevenir preus excessius, baixa qualitat en productes i serveis i d'altres irregularitats en el mercat. És essencial que qualsevol col·laboració entre empreses es realitzi de manera responsable i amb el propòsit de millorar els productes i serveis oferts als clients. | AG2: La gestió de riscos d'incidents crítics és rellevant per a organitzacions que duen a terme activitats o operacions perilloses. En aquest context, les organitzacions que identifiquen, comprenen, prevenen i minimitzen els riscos d'incidents que podrien ocórrer aconseguiran un millor acompliment en termes de sostenibilitat en la seva governança corporativa. Les empreses poden millorar el seu rendiment mitjançant la promoció d'una cultura de seguretat, la implementació de tecnologies que ajudin en la gestió de riscos, la realització d'anàlisi de probabilitat i impacte dels riscos i l'aplicació de mesures per mitigar aquests riscos, entre altres accions. | AH2: La gestió de riscos sistèmics s'enfoca a la contribució d'una empresa pel que fa als riscos sistèmics que amenacen els sistemes econòmics, socials, ambientals i tecnològics dels quals la societat depèn. Exemples d'aquests riscos inclouen el consum excessiu d'aigua per part d'una empresa que opera en una zona que ja pateix estrès hídric. Per millorar la seva gestió de la sostenibilitat, l'organització pot avaluar els seus impactes i aplicar plans i mesures de mitigació, entre altres accions. | AI2: La gestió de les cadenes de subministrament és essencial per supervisar les externalitats ambientals i socials generades per les activitats dels proveïdors. Dins de les cadenes de valor, poden sorgir problemes relacionats amb la responsabilitat ambiental, els drets humans, les condicions laborals, l'ètica i la corrupció, entre altres aspectes. La gestió de les cadenes de subministrament pot implicar l'avaluació, selecció, seguiment i compromís amb els proveïdors amb l'objectiu de reduir i mitigar els impactes mediambientals i socials. | AJ2: La resiliència del model de negoci fa referència a la capacitat de l'empresa d'adaptar-se als canvis relacionats amb les transicions ASG (mediambientals, socials i de bon govern). Això inclou la capacitat de mitigar riscos (com els reputacionals, legals i físics) i aprofitar les oportunitats que presenten els possibles nous mercats i productes i la diferenciació basada en la sostenibilitat. Les empreses més resilients compten amb sistemes de gestió de la sostenibilitat que identifiquen, avaluen i responen als riscos i les oportunitats potencials.
B3: Indicadors | AE3: - Composició de la junta directiva - % de membres independents dins la junta directiva - Existència de canals de denúncies i protecció de les parts interessades involucrades - % d'alts càrrecs investigats o condemnats - Compliment de codis (ètic, conducta, etc.) i normatives - % dels empleats (incloent-hi junta directiva) amb remuneració basada en la consecució d'objectius de sostenibilitat. - Auditories i certificacions independents | AI3: - % de proveïdors principals (valor de contractes) avaluats en temes de sostenibilitat - Petjada de carboni de la cadena de subministrament - % d'energia renovable en la cadena de subministrament - Reducció de residus i reciclatge dins de la cadena de subministrament (ecodisseny, embalatge, programes de retorn (take-back)) - Certificació mediambiental i social de proveïdors - Compliment dels drets laborals - Avaluació del cicle de vida dels productes
AT39: Alta relevancia
AT40: Relevancia significativa
AT41: Relevancia elevada
AT42: Sin especial relevancia

Sheet Fuentes
A1: Industria | B1: Tema | C1: Fuente | D1: URL
A2: Construcción | B2: Matrice de materialidad | C2: SASB: Home Builders | D2: https://sasb.org/standards/materiality-finder/find/?industry%5B0%5D=IF-EN
A3: Construcción | B3: Matrice de materialidad | C3: MSCI: Real Estate Development | D3: https://www.msci.com/our-solutions/esg-investing/esg-industry-materiality-map
A4: Servicios Técnicos de arquitectura e ingeniería | B4: Matrice de materialidad | C4: SASB: Engineering & Construction Services | D4: https://sasb.org/standards/materiality-finder/find/?industry%5B0%5D=IF-HB
A5: Servicios Técnicos de arquitectura e ingeniería | B5: Matrice de materialidad | C5: MSCI: Real Estate Services | D5: https://www.msci.com/our-solutions/esg-investing/esg-industry-materiality-map
A6: Publicidad (Marketing) | B6: Matrice de materialidad | C6: SASB: Advertising & Marketing | D6: https://sasb.org/standards/materiality-finder/find/?industry%5B0%5D=SV-AD
A7: Publicidad (Marketing) | B7: Matrice de materialidad | C7: SASB: Professional and Commercial Services | D7: https://sasb.org/standards/materiality-finder/find/?industry%5B0%5D=SV-PS
A8: Publicidad (Marketing) | B8: Matrice de materialidad | C8: MSCI: Advertising | D8: https://www.msci.com/our-solutions/esg-investing/esg-industry-materiality-map
A9: Hostelería | B9: Matrice de materialidad | C9: SASB: Restaurants | D9: https://sasb.org/standards/materiality-finder/find/?industry%5B0%5D=SV-AD
A10: Hostelería | B10: Matrice de materialidad | C10: MSCI: Restaurants | D10: https://www.msci.com/our-solutions/esg-investing/esg-industry-materiality-map
A11: Inmobilarias | B11: Matrice de materialidad | C11: SASB - Real Estate | D11: https://sasb.org/standards/materiality-finder/find/?industry%5B0%5D=IF-RE
A12: Inmobilarias | B12: Matrice de materialidad | C12: SASB - Real Estate Services | D12: https://sasb.org/standards/materiality-finder/find/?industry%5B0%5D=IF-RS
... A38: Venta y Reparación de Vehículos | B38: Matrice de materialidad | C38: SASB: Automobiles | D38: https://sasb.org/standards/materiality-finder/find/?industry%5B0%5D=TR-AU

Sheet Aliments i Begudes
D1: Indústria alimentària i de begudes | E1: Aquest grup d'activitats és la combinació de CNAE 10 (Indústria de l'alimentació) i CNAE 11 (Producció de begudes). L'enfocament es basa principalment en la fabricació de productes alimentaris i begudes processades. No obstant això, a causa de la importància de la cadena de valor per a la sostenibilitat d'aquestes activitats, es tindrà en compte com gestionar efectivament la sostenibilitat de la cadena de valor.
D3: Gestió sostenible de l'aigua | E3: Subministrament de matèries primeres / productes venuts | F3: Materials d'embalatge | G3: Qualitat de l'aire | H3: Emissions de GEH | I3: Gestió de residus i materials perillosos | J3: Biodiversitat i ecosistemes | K3: Seguretat química
B4: Descripció | C4: Medi ambient | D4: =HLOOKUP(D3,AUTO!$B$1:$AJ$2,2,FALSE) -> La gestió sostenible de l'aigua tracta d'assegurar que el consum i ús d'aquesta aigua per part de l'empresa estiguin alineats amb la capacitat de recuperar-se de l'ecosistema i no generin impactes negatius. Les necessitats de consumir aigua estan lligades al sector i a la ubicació de la planta. És important destacar que les empreses amb operacions en zones amb estrès hídric caldrà que avaluïn com fer una gestió sostenible dels recursos hídrics. Això inclou reduir el consum d'aigua, millorar la captura i reutilització de les aigües grises i millorar el tractament d'aigües residuals, entre d'altres. | E4: =HLOOKUP(E3,AUTO!$B$1:$AJ$2,2,FALSE) -> El subministrament de matèries primeres és un tema crucial per a la sostenibilitat d'aquells sectors molt intensius en materials. Aquí les empreses haurien d'avaluar oportunitats per a una adquisició de matèries de manera sostenible amb proveïdors confiables i certificats i estratègies de recuperació de material que es pugui recuperar com a matèria primera. Aquest tema pot ser important tant per a empreses que adquireixen matèries primeres com per a empreses que adquireixen prefabricats o productes. Un exemple és la cadena de subministrament d'empreses alimentàries, on és obligatori poder demostrar que el producte utilitzat no prové de zones amb alta deforestació. | F4: =HLOOKUP(F3,AUTO!$B$1:$AJ$2,2,FALSE) -> Els materials d'embalatge son part del dia a dia i en certs casos acaben a la natura. És important que el productor faci un exercici d'ecodisseny que asseguri el mínim ús de material i la màxima reciclabilitat. | G4: =HLOOKUP(G3,AUTO!$B$1:$AJ$2,2,FALSE) -> Les emissions de contaminants com el diòxid de sofre (SOx), el diòxid de nitrogen (NOx) i els Compostos Orgànics Volàtils (VOC), entre d'altres, poden tenir un impacte significatiu sobre la qualitat de l'aire. Una mala qualitat de l'aire pot tenir efectes negatius tant sobre el medi ambient com sobre la salut de les comunitats afectades. Per tant, les empreses que duen a terme operacions que produeixen emissions a l'aire han d'avaluar el seu impacte sobre la qualitat de l'aire mitjançant controls regulars duts a terme per l'autoritat ambiental competent. Les empreses podrien considerar la instal·lació de filtres i altres mesures destinades a reduir les emissions de contaminants atmosfèrics. | H4: =HLOOKUP(H3,AUTO!$B$1:$AJ$2,2,FALSE) -> Les emissions de gasos amb efecte d'hivernacle i les energies renovables són categories estretament vinculades amb el canvi climàtic. Les empreses amb una major petjada de carboni contribueixen en major mesura al canvi climàtic. Reduir els impactes relacionats amb aquest tema requereix una reducció de la petjada de carboni de l'empresa. Això requereix una transició envers fonts d'energia renovables i la implementació d'estratègies per assolir emissions netes zero. | I4: =HLOOKUP(I3,AUTO!$B$1:$AJ$2,2,FALSE) -> La gestió de residus perillosos i no perillosos és un àmbit en constant evolució normativa. L'adequada gestió de residus i materials perillosos és clau per reduir la contaminació causada per l'empresa o els productes que posa al mercat. Optimitzar el disseny i la producció i treballar paral·lelament a millorar la gestió de residus és clau per transicionar envers una economia circular que redueixi la necessitat d'explotació de nous recursos naturals. Per tant, les empreses que gestionen els seus residus i eviten la seva generació són més sostenibles i estan més alineades amb els principis de l'economia circular. | J4: =HLOOKUP(J3,AUTO!$B$1:$AJ$2,2,FALSE) -> Aquesta categoria se centra en els impactes de les operacions o els actius d'una empresa sobre ecosistemes i la seva biodiversitat. Les activitats amb potencials impactes significatius són aquelles vinculades amb canvis en l'ús del sòl per a exploració/explotació de recursos naturals, construcció, agricultura extensiva, etc. Els impactes poden produir pèrdua de biodiversitat, destrucció d'hàbitats, deforestació i pèrdua de serveis ecosistèmics bàsics. Les empreses haurien d'avaluar les seves dependències i impactes sobre el capital natural (natura), mitigar els riscos associats i fomentar un impacte positiu en totes les fases de la cadena de valor de l'empresa. | K4: =HLOOKUP(K3,AUTO!$B$1:$AJ$2,2,FALSE) -> Garantir la seguretat química és de gran importància per preservar els ecosistemes i protegir les comunitats properes a instal·lacions que empren substàncies químiques perilloses. Les empreses que comercialitzen productes que contenen substàncies químiques perilloses susceptibles d'entrar en contacte amb l'entorn natural o els usuaris d'aquests productes és essencial que prenguin totes les mesures necessàries per prevenir aquesta situació. Millorar la seguretat química pot implicar la recerca d'alternatives de materials per a l'ús en els seus productes, dissenyar productes de manera segura per prevenir fuites de substàncies i elaborar un pla de gestió de residus al final del cicle de vida del producte.
B5: Indicadors | D5: - Petjada hídrica total de l'empresa + Cadena de subministrament + Operacions directes + Distribució - Consum total d'aigua - Consum d'aigua per volum de negocis (€) - Consum d'aigua per producte (nombre o pes) - Consum d'aigua en àrees amb estrès hídric - Descàrrega total d'aigua - Descàrrega total d'aigua en àrees amb estrès hídric - % de reutilització de l'aigua | E5: - % d'ingredients adquirits amb certificació de sostenibilitat - % dels principals proveïdors auditats en temes de sostenibilitat - Emissions de CO2 per kg d'ingredient (abast 3) - Consum d'aigua per kg o litre d'ingredient - Hectàrea de conversió de la terra (per exemple, deforestació) - % pèrdues/malbaratament alimentari generades en relació amb l'entrada de productes - Costos estalviats per l'aprofitament dels productes enretirats que no han esdevingut pèrdues/malbaratament alimentaris | F5: - Reducció en pes/volum de materials d'embalatge - % de materials reciclats en embalatge - % de materials d'embalatge reciclables - Materials òrganics (en situacions on el reciclatge no és viable) | G5: - Emissions de SOx, NOx i Compostos Orgànics Volàtils (VOC) - Mesurament de la qualitat de l'aire interior - Emissions de NOx dels vehicles de transport a les ciutats | H5: - Petjada de carboni de l'empresa (abast 1, 2 i 3), incloent: + emissions relacionades amb els combustibles fòssils + emissions relacionades amb l'electricitat i el vapor adquirit + emissions de gasos refrigerants (recàrregues d'equips frigorífics) + Altres emissions vinculades amb els materials usats, viatges per a negocis, etc. - Capacitat per generar energia renovable - Canvis d'emissions i capacitat de renovables | I5: - Generació total de residus - Generació de residus perillosos - Generació de residus no perillosos - % de residus destinats a eliminació - % de residus destinats a reutilització o reciclatge - % de productes dissenyats segons principis d'ecodisseny - % de pèrdues/malbaratament alimentaris generades en relació amb el volum de negoci de l'organització - % generació de pèrdues/malbaratament alimentaris per procés | J5: - Àrea de conversió dels ecosistemes (per exemple: deforestació o conversió de bosc verge a cultius) + Generat per les operacions mateixes + Generat per la cadena de valor - Abundància mitjana d'espècies - Canvis en l'abundància mitjana d'espècies | K5: - % dels ingredients/materials que compleixen la legislació UE d'agroquímics o certificacions de sostenibilitat - % dels ingredients de fonts orgàniques - Reducció en l'ús d'agroquímics en la cadena de valor - Ús total (pes o volum) de químics identificats en els processos de producció - Reducció en l'ús de químics identificats en els processos de producció - % del personal que treballa amb químics que tenen la formació adequada
C6: Social | D6: Seguretat i qualitat del producte | E6: Oportunitats de nutrició i salut | F6: Salut i seguretat laboral | G6: Estàndards de treball en la cadena de valor | H6: Practiques de venda i etiquetatge | I6: Desenvolupament del capital humà
B7: Descripció | D7: =HLOOKUP(D6,AUTO!$B$1:$AJ$2,2,FALSE) -> La seguretat i qualitat són aspectes importants del producte, no només des d'una perspectiva econòmica, sinó també des d'una perspectiva de sostenibilitat. Falles de seguretat i/o qualitat del producte poden afectar negativament la salut o la seguretat dels usuaris, la qual cosa pot produir una varietat de riscos tant per a la reputació de l'empresa com legals. Algunes de les mesures que les empreses poden prendre per gestionar aquests riscos són dur a terme proves de productes i gestionar el contingut, els ingredients i els químics utilitzats en el producte. | E7: =HLOOKUP(E6,AUTO!$B$1:$AJ$2,2,FALSE) -> Particularment en la indústria alimentària i de begudes, les oportunitats relacionades amb la nutrició i la salut són fonamentals per proporcionar productes de més qualitat als consumidors. Des d'una perspectiva de sostenibilitat social, és crucial que les empreses aprofitin les oportunitats per oferir productes amb un major valor nutricional i beneficis per a la salut dels consumidors. Aquelles empreses que aprofiten aquestes oportunitats poden destacar en el mercat, la qual cosa al seu torn contribueix a la seva sostenibilitat econòmica. | F7: =HLOOKUP(F6,AUTO!$B$1:$AJ$2,2,FALSE) -> La salut i seguretat laboral hauria de ser una prioritat fonamental en qualsevol empresa. Totes les empreses han d'assegurar-se de proporcionar un entorn de treball segur i saludable per als seus empleats. Això és especialment crucial en aquelles empreses que duen a terme operacions perilloses o tenen el potencial d'afectar adversament la salut dels seus treballadors. Una de les mesures clau per assegurar la salut i seguretat dels empleats és designar un/a responsable de salut i seguretat la funció principal del qual consisteix a avaluar els riscos per als empleats i implementar mesures de mitigació corresponents. | G7: =HLOOKUP(G6,AUTO!$B$1:$AJ$2,2,FALSE) -> És crucial mantenir alts estàndards laborals i condicions de treball dignes per a tots els empleats en la cadena de valor. L'empresa s'ha d'assegurar que tots els seus proveïdors respectin els drets laborals i humans, la qual cosa inclou garantir una remuneració justa, horaris laborals adequats i la prohibició del treball forçós i el treball infantil. Per assegurar condicions laborals acceptables en tota la cadena de valor, l'empresa pot requerir el compliment d'un codi de conducta per part dels seus proveïdors i dur a terme auditories en alguns d'ells per verificar-ne el compliment. | H7: =HLOOKUP(H6,AUTO!$B$1:$AJ$2,2,FALSE) -> És essencial mantenir Bones Pràctiques en la venda i l'etiquetatge de productes per prevenir qualsevol pràctica enganyosa. Les pràctiques enganyoses poden portar els consumidors a triar un producte que no s'ajusti a les seves necessitats o requeriments. Per tant, per garantir Bones Pràctiques en la venda i l'etiquetatge, una empresa ha de gestionar la transparència de la informació relacionada amb els seus productes, operacions i cadenes de valor. A més, és fonamental proporcionar informació precisa i rellevant sobre els productes, sense ocultar desavantatges o altres tipus d'informació d'interès. | I7: =HLOOKUP(I6,AUTO!$B$1:$AJ$2,2,FALSE) -> El desenvolupament del capital humà pot ser un factor important per a empreses en sectors que requereixen coneixements o habilitats específiques. Les empreses que no inverteixen en el desenvolupament dels seus empleats poden perdre competitivitat en el mercat laboral, la qual cosa pot afectar la seva capacitat d'atreure i mantenir personal capacitat. Per assegurar la sostenibilitat social i econòmica en el futur, l'empresa pot oferir oportunitats de creixement al seu personal. En la mateixa línia, per mantenir una posició competitiva al mercat, les empreses han d'invertir en la formació i educació dels seus empleats.
B8: Indicadors | D8: - Taxa de queixes sobre els productes - Taxa d'enretirades dels productes - Taxa de no-conformitats amb requisits de qualitat i/o seguretat - Taxa de contaminació per objectes estranys - Seguretat microbiològica - Gestió d'al·lèrgens - Vida útil del producte | E8: - Contingut de sucres, greixos i sal - Índex de nutrients crítics (vitamines, minerals i fibres) - Contingut nutricional beneficiós - Nombre de productes saludables - Percentatge de vendes de productes saludables - Compliment de l'etiquetatge nutricional - Inversió en recerca i desenvolupament en nutrició saludable | F8: - Taxa d'accidentalitat (per x empleats o per x hores treballades) - Índex de freqüència d'accidents (i canvis respecte d'altres anys) - Índex de gravetat d'accidents - Taxa de malalties laborals - Participació en formacions de seguretat - Taxa de compliment de procediments de seguretat - Nombre d'inspeccions de seguretat realitzades - Freqüència d'avaluació dels riscos laborals | G8: - % de compliment de proveïdors de les normatives laborals - % d'empleats amb contractes formals - Proveïdors certificats socialment (% valor dels contractes) - Participació dels proveïdors en iniciatives de responsabilitat social - Nombre de proveïdors auditats per condicions laborals - Ús d'equips de protecció personal - Disponibilitat d'assistència mèdica - Disponibilitat d'aigua potable i serveis sanitaris | H8: - % dels productes en venda que compleixen la legislació d'etiquetes - Nombre de denúncies de pràctiques de publicitat, venda o etiquetatge enganyosos - Nombre d'instàncies on l'empresa ha hagut d'adaptar la publicitat d'un producte per informació falsa | I8: - Hores de formació per empleat - % de promocions internes i de lideratge intern - Avaluació de l'acompliment personalitzat - Participació en programes de desenvolupament professional - Diversitat i inclusió (representació de minories) - % d'empleats amb plans de desenvolupament personalitzats - Taxa de retenció d'empleats
C9: Governança | D9: Bon govern | E9: Gestió de la cadena de subministrament
B10: Descripció | D10: =HLOOKUP(D9,AUTO!$B$1:$AJ$2,2,FALSE) -> El bon govern és un tema ampli, enfocat en la gestió responsable i ètica de l'organització en general. L'acompliment de bon govern està vinculat als codis ètics de l'empresa, l'estructura de la propietat i el control de l'empresa, la junta directiva (i la seva remuneració), una comptabilitat transparent, la política fiscal i la transparència. | E10: =HLOOKUP(E9,AUTO!$B$1:$AJ$2,2,FALSE) -> La gestió de les cadenes de subministrament és essencial per supervisar les externalitats ambientals i socials generades per les activitats dels proveïdors. Dins de les cadenes de valor, poden sorgir problemes relacionats amb la responsabilitat ambiental, els drets humans, les condicions laborals, l'ètica i la corrupció, entre altres aspectes. La gestió de les cadenes de subministrament pot implicar l'avaluació, selecció, seguiment i compromís amb els proveïdors amb l'objectiu de reduir i mitigar els impactes mediambientals i socials.
B11: Indicadors | D11: - Composició de la junta directiva - % de membres independents dins la junta directiva - Existència de canals de denúncies i protecció de les parts interessades involucrades - % de denúncies investigades - Compliment de codis (ètic, conducta, etc.) i normatives - % dels empleats (incloent-hi la junta directiva) amb remuneració basada en acompliment de sostenibilitat - Auditories i certificacions independents | E11: - % de proveïdors principals (valor de contractes) avaluats en temes de sostenibilitat - Petjada de carboni de la cadena de subministrament - % d'energia renovable en la cadena de subministrament - Reducció de residus i reciclatge dins de la cadena de subministrament (ecodisseny, embalatge, programes de retorn) - Certificació mediambiental i social de proveïdors - Compliment dels drets laborals - Avaluació del cicle de vida de productes - % generació de pèrdues/malbaratament alimentaris per causa de generació vinculada a processos externs (transport, proveïdor, altres)
B13: Mesures de gestió generals
B14: Tema | C14: Aplica a | D14: Descripció | E14: Font
B15: Bon govern - conducta de negocis | C15: Totes | D15: Comptar amb un codi de conducta que estableixi normes per a tots els empleats. Aquest document s'haurà d'alinear amb les normatives vigents per al sector, incloent especialment temes ambientals (contaminació de l'aire, aigua, sòl, impactes sobre la biodiversitat, emissions GEH, etc.), drets humans, condicions laborals, seguretat, anticorrupció i suborn, promoció de la igualtat (de gènere) i la inclusió de tothom. | E15: Consulteu més informació sobre el codi de conducta
B16: Bon govern - control de qualitat | C16: Totes | D16: L'empresa ha d'establir un sistema de gestió i control de qualitat per a tots els serveis i productes oferts a fi d'assegurar la qualitat del producte i la seguretat per als clients. És una bona pràctica certificar aquest sistema de gestió amb una ISO9001. | E16: Vegeu informació sobre la ISO 9001
B17: Impactes ambientals - sistema de gestió ambiental | C17: Totes | D17: L'empresa ha d'establir un sistema de gestió mediambiental que permeti identificar i avaluar els impactes potencials i reals i els riscos i les oportunitats relacionats amb la sostenibilitat de l'empresa. Els marcs per desenvolupar un sistema de gestió mediambiental són l'EMAS de la Unió Europea i la ISO14001. | E17: Consulteu informació sobre EMAS
E18: Vegeu informació sobre la ISO 14001.
B19: General - estat d'informe no financer | C19: Totes | D19: Els requisits de divulgació d'informació no financera, especialment pel que fa a la sostenibilitat, estan guanyant rellevància tant per a inversors com per a organismes públics. Aquesta tendència es troba estretament vinculada amb les regulacions de la Unió Europea en el marc del Pla de finances sostenibles i el Pacte verd. Tant la Directiva d'informació corporativa sostenible (CSRD) com la Llei 11/2018 harmonitzen els requisits de divulgació per a les grans empreses. Aquestes i altres iniciatives estan generant un efecte dominó sobre les cadenes de valor i el sistema financer, la qual cosa està portant a una major demanda d'informació per part d'empreses de totes les mides. Per tant, la divulgació d'informació sobre sostenibilitat reforça la posició d'una empresa en el mercat. Per a les petites i mitjanes empreses (PIME) que volen començar a divulgar informació no financera, el marc de referència GRI pot servir com a base. | E19: Consulteu més informació sobre la CSRD
E20: Consulteu la Llei 11/2018
E21: Consulteu més informació sobre el marc GRI
B22: Medi ambient - eficiència energètica | C22: Totes | D22: L'eficiència energètica exerceix un paper fonamental en la reducció de les emissions de gasos amb efecte d'hivernacle de qualsevol empresa. Millorar l'eficiència energètica permet a una empresa generar valor amb un menor ús de recursos escassos. El document BREF de la Unió Europea proporciona orientació específica per assolir un ús eficient dels recursos i l'energia en diversos sectors i promou l'adopció de pràctiques sostenibles i alineades amb els objectius de la UE. Això no només beneficia la sostenibilitat econòmica de l'empresa, sinó que també contribueix a combatre el canvi climàtic. | E22: Consulteu el Document de referència sobre les millors tecnologies disponibles en termes d'eficiència energètica
B23: Protecció de dades - política de protecció de dades | C23: Totes | D23: L'empresa ha d'establir una política de protecció de dades, alineades amb la llei de protecció de dades de la UE. Tot el personal ha de rebre formació per gestionar dades del client de manera adequada i hi ha d'haver un protocol de contigència per a casos d'emergència. Adjunt a la columna de fonts trobareu un exemple d'una política de protecció de dades de l'Agència Catalana de Turisme. | E23: Consulteu un exemple d'una política de protecció de dades
B24: Bon govern - conducta de proveïdors | C24: Totes | D24: L'empresa ha d'establir un codi de conducta per als seus proveïdors i altres actors en la cadena de valor del negoci. Aquest codi ha de ser signat pels proveïdors i exigir-ne el compliment amb els estàndards de bon govern establerts en el document. Es recomana alinear aquest codi de conducta amb el codi de conducta intern, encara que en certs casos es pot permetre certa flexibilitat, sempre que continuï estant de conformitat amb les regulacions vigents relacionades amb la cadena de valor, com aquelles relacionades amb la no deforestació, els drets humans o les emissions de carboni, entre d'altres. A la columna 'Fonts' adjunta, trobareu un exemple d'un codi de conducta/ètic per a proveïdors del Pacte Mundial de Nacions Unides. | E24: Consulteu un exemple de codi de conducta/ètica de proveïdors
B25: Social - Pla d'igualtat de gènere | C25: Empreses amb més de 50 treballadors | D25: L'empresa ha d'implementar un pla d'igualtat de gènere en compliment del Reial decret 901/2020. Aquest requisit implica que les empreses han d'adoptar, amb negociació prèvia, mesures destinades a prevenir qualsevol forma de discriminació laboral entre dones i homes i a fomentar condicions de treball que evitin l'assetjament sexual i l'assetjament per raó de gènere. A més, han d'establir procediments específics per a la prevenció d'aquests comportaments i per gestionar les denúncies o reclamacions presentades per qui n'hagi estat víctima. | E25: Consulteu el Reial decret 901/2020
B26: Medi ambient - circularitat | C26: Totes | D26: Catalunya Circular és el hub d’innovació i punt de trobada d’empreses i institucions que aporten solucions i estratègies per consolidar l’economia circular a Catalunya. | E26: Consulta informació sobre Catalunya Circular, l'Observatori d'economia circular
E27: Consulteu més informació sobre l'economia circular (Fundació Ellen McArthur)
E28: Consulteu informació sobre el certificat Cradle to Cradle
B29: Medi ambient - residus | C29: Totes | D29: A partir de l'1 de gener de 2023, va entrar en vigor la Llei 7/2022, de 8 d'abril, de residus i sòls contaminats per una economia circular, que amplia la responsabilitat del productor de residus fins que aquests residus hagin estat gestionats per un gestor final. Això té implicacions per a totes les empreses que generen residus, ja que s'han d'assegurar que els residus siguin tractats o eliminats de manera adequada. A més, la Llei estableix que el productor de residus ha de fer separacions mínimes o garantir que un gestor les realitzi. També se li exigeix prioritzar la prevenció de la generació de residus per sobre de la reutilització, i aquesta per sobre del reciclatge, i aquest últim per sobre de l'eliminació. Finalment, s'han de donar prioritat als gestors ubicats geogràficament a prop. L'Agència de Residus de Catalunya té competència sobre els residus que es generen a Catalunya i els que es gestionen al seu àmbit territorial. Queden exclosos de la seva competència els residus radioactius, els residus resultants de la prospecció, l’extracció, el tractament i l’emmagatzematge de recursos minerals i de l’explotació de pedreres, els residus d’explotacions agrícoles i ramaderes que no siguin perillosos i s’utilitzin exclusivament en el marc de l’explotació agrària, els explosius desclassificats, les aigües residuals i els efluents gasosos emesos a l’atmosfera. | E29: Consulteu la Llei 7/2022
E30: Consulteu més informació sobre normativa catalana en matèria de residus
B31: Medi ambient - materials d'embalatge | C31: Totes | D31: Atès que la indústria manufacturera produeix productes físics, els materials d'embalatge utilitzats per al transport i la distribució d'aquests productes són un factor crucial amb un impacte potencialment significatiu. Per aquesta raó, la Unió Europea ha implementat una nova legislació que requereix la reducció de l'ús de plàstics d'un sol ús i en prohibeix certes aplicacions. A més, des de l'1 de gener, va entrar en vigor la Llei 7/2022, que estableix un nou impost sobre els envasos de plàstic no reutilitzables. Per tant, és important cercar materials d'embalatge que generin un menor impacte sobre el medi ambient, adaptats a l'aplicació i la ubicació geogràfica dels productes. La Sustainable Packaging Coalition ofereix diverses iniciatives destinades a ajudar les empreses a reduir l'impacte ambiental dels seus envasos. | E31: Consulteu informació sobre el Sustainable Packaging Coalition
E32: Consulteu informació sobre la Llei de plàstics d'un sol ús
E33: Consulteu informació sobre impostos sobre els envasos de plàstic no reutilitzables
B34: Medi ambient - compra sostenible | C34: La compra d'actius o productes | D34: Optar per actius o productes amb característiques d'eficiència i durabilitat contribueix a la reducció del consum de recursos i a la minimització de residus. Això no només té un impacte positiu sobre l'empremta ambiental, sinó que també pot generar estalvis operatius a llarg termini. Un exemple destacat és l'EU Ecolabel, una certificació ecològica reconeguda a la Unió Europea. Els productes que tenen aquesta etiqueta compleixen estàndards rigorosos de sostenibilitat en termes d'eficiència, materials i longevitat. En triar articles amb l'EU Ecolabel, les empreses poden demostrar el seu compromís amb pràctiques responsables i avançar cap a una operació més sostenible i respectuosa envers l'entorn. | E34: Consulteu informació sobre l'EU Ecolabel
B35: Medi ambient - Emissions de carboni | C35: Totes | D35: El transport de materials i productes contribueix al canvi climàtic a causa de les emissions de carboni que genera. Si bé és possible reduir la petjada de carboni en les activitats mateixes mitjançant l'ús d'energies renovables, el transport en si també té un impacte significatiu. Per aquesta raó, és important considerar formes de transport sostenible, com ara mitjans de transport respectuosos envers el medi ambient o la selecció de proveïdors locals, entre altres mesures. En el sector de la logística, hi ha iniciatives destinades a reduir les emissions d'aquest sector. Un exemple d'aquestes iniciatives és Lean and Green, que ajuda les empreses logístiques a reduir les seves emissions i compta amb un sistema de classificació basat en el seu acompliment. | E35: Consulteu informació sobre la iniciativa Lean and Green
E36: Consulteu informació sobre l'Oficina Catalana de Canvi Climàtic
B37: Medi ambient - compra sostenible - proveïdors | C37: Totes | D37: És important avaluar la sostenibilitat dels possibles proveïdors i donar prioritat a aquells que tenen el millor acompliment en aspectes ambientals, socials i de governança (ESG). Per garantir la compra sostenible, les empreses poden establir una política de compra sostenible per a tots els seus proveïdors, avaluar i prioritzar els proveïdors segons el seu acompliment en ASG i certificacions de sostenibilitat de productes, com l'EU Ecolabel, i col·laborar per assegurar una millora contínua, entre altres mesures. Actualment, la Unió Europea està desenvolupant legislació per exigir a les grans empreses que garanteixin la sostenibilitat en les seves compres, en forma del CSDDD (Corporate Sustainable Due Diligence Directive proposal). | E37: Vegeu la ISO 20400:2017 sobre compra sostenible
E38: Consulteu informació sobre l'EU Ecolabel
B39: Social - Estratègia Catalana de Seguretat i Salut Laboral | C39: Totes | D39: L’Estratègia catalana de seguretat i salut laboral 2021-2026 té com a objectiu millorar les condicions de treball a Catalunya, reduir la sinistralitat laboral i promoure la prevenció de riscos laborals. És fruit del treball conjunt entre la Generalitat, patronals i sindicats, amb indicadors per avaluar-ne el progrés i una perspectiva de gènere transversal. | E39: Consulta informació sobre l'estratègia Catalana de Seguretat i Salut Laboral
B40: Bon govern - Pla de govern de la Generalitat de Catalunya | C40: Totes | D40: Aquest Pla contempla un eix dedicat a la "Transformació Democràtica", que inclou aspectes com el "Bon govern i govern obert". Aquest enfocament pot ser rellevant per al sector, ja que promou la transparència, l'ètica i la responsabilitat en les pràctiques de govern, que poden ser aplicades o servir d'exemple per a les empreses del sector​. | E40: Consulta informació sobre el Pla de govern de la Generalitat de Catalunya
B43: Temes específics per a la indústria alimentària i de begudes
B44: Tema | C44: Aplica a | D44: Descripció | E44: Font
B45: Diversos - Estratègia UE De la granja a taula (Farm to Fork) | C45: Diversos | D45: Per millorar la sostenibilitat del sector alimentari, la Unió Europea ha desenvolupat una estratègia De la granja a taula (Farm to Fork) que proposa una varietat de mesures i legislacions amb aquesta finalitat. Aquestes mesures inclouen el codi de conducta per fomentar la responsabilitat dels negocis en el sector i estimular la publicitat honesta sobre els productes. Addicionalment, s'ha implementat una iniciativa per reformular el menjar processat que estableix valors màxims per a certs ingredients. També s'està treballant en la implementació d'un perfil de nutrients del menjar per restringir la promoció de productes alts en greix, sal i sucre. Amb l'objectiu de salvaguardar la seguretat dels aliments, s'ha proposat una revisió de la legislació de materials que poden estar en contacte amb aliments durant el procés de producció i distribució. | E45: Consulteu l'Estratègia De la granja a taula (Farm to Fork)
B46: Medi ambient - subministrament de matèries primeres: Rain Forest Alliance | C46: Bananes, cacau, cafè, fruita, espècies, nous, oli de palma, te | D46: Rainforest Alliance és una ONG que promou la producció sostenible de matèries primeres agrícoles. Aquesta organització ofereix una certificació a les empreses del sector alimentari que els permet demostrar el seu compromís i compliment amb pràctiques de producció agrícola sostenible. Els requisits per obtenir aquesta certificació són amplis i abasten aspectes socials, mediambientals i de bon govern. Estableix requisits tant per als actors dins de la cadena de valor que utilitzen les matèries primeres com per als productors. En tots dos casos, s'enfoca en la traçabilitat i la responsabilitat dels negocis. Els requisits per als agricultors inclouen aspectes més concrets relacionats amb la sostenibilitat mediambiental com ara la conservació dels boscos, la gestió de l'aigua, la gestió de residus, l'eficiència energètica o l'ús d'agroquímics, entre d'altres. També incorpora requisits per garantir la sostenibilitat social, com ara el pagament de salaris dignes, la protecció dels infants i el respecte envers les comunitats locals, entre d'altres. | E46: Consulteu el marc RFA - Supply Chain Requirements
E47: Consulteu el marc RFA - Requisits per a agricultors
B48: Social / diversos: Fairtrade | C48: Cacau, cafè, sucre, te, bananes, fruites | D48: Originalment, la certificació Fairtrade se centrava principalment en aspectes socials amb l'objectiu de defensar els drets dels treballadors en la cadena de valor. Alguns dels temes socials incorporats en la certificació Fairtrade són antidiscriminació, protecció de nens, condicions laborals (incloent-hi retribució justa i hores limitades) i seguretat laboral. Avui, la certificació Fairtrade també ha incorporat temes ambientals per al sector alimentari. Això inclou l'ús mínim i segur d'agroquímics, la gestió de residus, la fertilitat de sòls i la gestió sostenible de recursos hídrics. | E48: Consulteu informació sobre la certificació Fairtrade
B49: Medi ambient - subministrament de matèries primeres: SAI-FSA | C49: Una gran varietat de productes agrícoles | D49: Els estàndards de SAI-FSA estableixen un nivell mínim de sostenibilitat per a una àmplia varietat de productes agrícoles. Aquesta certificació és utilitzada per grans empreses per supervisar i garantir la sostenibilitat de la seva cadena de valor. Els requisits de la certificació abasten una àmplia gamma de temes que van des de la gestió sostenible de l'aigua fins a la limitació en l'ús d'agroquímics, passant per la garantia d'un salari digne per als agricultors i el respecte dels drets de les comunitats afectades. | E49: Consulteu informació sobre el SAI-FSA
B50: Medi ambient - Taula rodona per a l'oli de palma sostenible | C50: Oli de palma | D50: L'oli de palma és un dels ingredients més comuns en productes alimentaris, entre d'altres. La producció d'aquest oli es duu a terme en països tropicals, on la producció d'oli de palma pot causar un risc per a les selves natives de la zona. Per combatre la deforestació i salvaguardar els drets de comunitats (indigenes) locals, s'ha creat una col·laboració en forma d'una taula rodona per a l'oli de palma sostenible. En aquesta taula rodona, s'han acordat certs principis i criteris per a la producció ambiental i socialment sostenible d'aquesta matèria primera. Qualsevol actor dins de la indústria alimentària hauria d'avaluar aquest ingredient i valorar la sostenibilitat de la seva cadena de valor. | E50: Consulteu els RSPO Principis i Criteris
B51: Medi ambient - impactes ambientals: agricultura regenerativa | C51: Totes | D51: Les tècniques d'agricultura tradicional generen impactes ambientals significatius. Els monocultius a gran escala redueixen la biodiversitat i la salut i fertilitat del sòl, la qual cosa afecta els ecosistemes i la fauna que hi habita. Per mitigar aquests impactes, alguns agricultors estan adoptant tècniques agrícoles que preserven i fins i tot regeneren la biodiversitat i la salut dels ecosistemes. Exemples d'aquestes tècniques inclouen l'agricultura regenerativa i l'agroforesteria. Qualsevol empresa que utilitzi ingredients agrícoles en els seus productes finals hauria d'avaluar com contribuir a la reducció d'aquests impactes. | E51: Consulteu informació sobre l'agricultura regenerativa
B52: Medi ambient - malbaratament alimentari | C52: Totes | D52: El malbaratament dels aliments genera nombrosos impactes socials i ambientals. Atès el creixement constant de persones que necessiten aliments, el malbaratament dels aliments esdevé un problema crític. S'estima que aproximadament el 30% de tots els aliments produïts es malbaraten en algun punt de la cadena de valor. Això implica que els recursos invertits, les emissions i el altres impactes ambientals han estat en va. Per abordar aquest problema, la Comissió Europea ha proposat fites obligatòries de reducció del rebuig d'aliments. A més, hi ha coalicions voluntàries, com la International Food Waste Coalition, que comparteixen informació i coneixements sobre la reducció del rebuig d'aliments entre els seus socis. | E52: Consulteu la proposta de la UE per a objectius de reducció del residu alimentari
E53: Consulteu la LlEI 3/2020, d'11 de març, de prevenció de les pèrdues i el malbaratament alimentaris
E54: Consulteu la Guia per a la integració de la prevenció de les pèrdues i el malbaratament alimentaris als sistemes de gestió ambiental
E55: Guia per a la implantació d'un pla de prevenció i reducció de les pèrdues i el malbaratament alimentaris a les empreses agroalimentàries
E56: Consulteu informació sobre la International Food Waste Coalition
B57: Diversos - millors tecnologies disponibles | C57: Totes | D57: L'adopció de les millors tecnologies disponibles, recolzades pels documents BREF, és de summa rellevància per a la indústria d'aliments i begudes en termes de sostenibilitat. Aquestes tecnologies avançades optimitzen l'eficiència dels processos, redueixen el consum de recursos i minimitzen la generació de residus i emissions. En seguir les directrius dels documents BREF, les empreses poden millorar el seu acompliment en sostenibilitat i alinear-se amb els estàndards europeus reconeguts. A més, aquestes pràctiques milloren la imatge de marca en demostrar un compromís ambiental i social, la qual cosa atrau consumidors preocupats per la sostenibilitat. | E57: Consulteu el document BREF sobre les millors tecnologies d'aliments, begudes i llet
E58: Consulteu el document BREF sobre les millors tecnologies de la preparació d'ocells de corral i porcs
E59: Consulteu el document BREF sobre les millors tecnologies d'escorxadors
B60: Medi ambient - Distintiu de garantia de qualitat ambiental | C60: Totes | D60: El Distintiu de garantia de qualitat ambiental és una etiqueta oficial que atorga la Generalitat de Catalunya a productes i serveis que superen determinats requisits de qualitat ambiental més enllà dels establerts com a obligatoris per la normativa vigent. Està dissenyat per ajudar els consumidors a identificar productes i serveis que han estat produïts de manera responsable i sostenible. | E60: Consulteu informació sobre el Distintiu de garantia de qualitat ambiental específic per a molins d'oli
B61: Social - Projectes estratègics de desenvolupament econòmic local | C61: Totes | D61: Els projectes estratègics de desenvolupament econòmic local tenen l'objectiu d'analitzar, planificar i definir el conjunt d’estratègies, actuacions, projectes i programes orientats a enfortir les economies locals amb la finalitat de millorar la qualitat de vida i el benestar de les persones a partir d’un desenvolupament econòmic sostenible estretament lligat a un àmbit territorial local determinat, i avaluar-ne els resultats. Ofereix recursos de formació al món rural, estretament lligat al sector agroalimentari. | E61: Consulta informació sobre els projectes estratègics de desenvolupament econòmic local
B62: Diversos - Pla de Seguretat Alimentària de Catalunya | C62: Totes | D62: El Pla de seguretat alimentària de Catalunya 2022-2026, aprovat pel Govern de Catalunya el 7 de juny de 2022, té com a objectiu mantenir l’alt nivell de seguretat alimentària i alhora contribuir a consolidar el prestigi dels productes alimentaris catalans en el mercat nacional i internacional. És l’instrument estratègic de referència de la intervenció pública en aquesta matèria. | E62: Consulta informació sobre el Pla de seguretat alimentària de Catalunya 2022-2028
B63: Social - Pautes per a la gestió conjunta dels sistemes d’autocontrol de la Qualitat i Seguretat Alimentàries basats en l’Anàlisi de perills i punts de control crític (APPCC) | C63: Totes | D63: Conté materials del Departament d'Acció Climàtica, Alimentació i Agenda Rural de la Generalitat de Catalunya, per facilitar a les PIME agroalimentàries la implantació del sistema d’autocontrol de la qualitat: cursos de formació, MUCAI (Mínima Unitat de Coneixements Adquirits Individuals) en qualitat agroalimentària i altres materials com ara guies, fitxes informatives sobre etiquetatge i aspectes crítics de qualitat elaborades per la Subdirecció General de la Inspecció i el Control Agroalimentaris i documents interpretatius disponibles al lloc web del Departament. | E63: Consulta informació sobre les Pautes per a la gestió conjunta dels sistemes d’autocontrol de la Qualitat i Seguretat Alimentàries basats en l’APPCC
B64: Diversos - Codi de bones pràctiques comercials (CBPC) a la cadena alimentària de Catalunya | C64: Totes | D64: El Departament d’Acció Climàtica, Alimentació i Agenda Rural de la Generalitat de Catalunya, lidera una iniciativa voluntària que involucra tots els actors de la cadena alimentària amb l’objectiu de millorar les relacions, la transparència, l’eficiència i la valorització dels productes agroalimentaris. A més, se cerca impulsar la comercialització local, l’eficiència tecnològica i la resolució de conflictes entre empreses. Publicat l’any 2011. | E64: Consulta informació sobre el Codi de bones pràctiques comercials (CBPC) a la cadena alimentària de Catalunya

Sheet Moda i tèxtil
D1: Indústria de la moda i tèxtil | E1: Aquesta indústria és una agrupació d'activitats CNAE 13, 14 i 15 relacionades amb tèxtils, peces de vestir i cuir. En aquests sectors, la cadena de subministrament pren un paper important, atès que una gran part dels impactes mediambientals i socials es concentren en altres parts del món. Tanmateix, també és important avaluar la sostenibilitat de les activitats mateixes.
D3: Gestió sostenible de l'aigua | E3: Subministrament de matèries primeres / productes venuts | F3: Emissions de GEH | G3: Qualitat de l'aire | H3: Disseny del producte i gestió del cicle de vida | I3: Eficiència energètica i energies renovables | J3: Seguretat química
B4: Descripció | C4: Medi ambient | D4: =HLOOKUP(D3,AUTO!$B$1:$AJ$2,2,FALSE) -> La gestió sostenible de l'aigua tracta d'assegurar que el consum i ús d'aquesta aigua per part de l'empresa estiguin alineats amb la capacitat de recuperar-se de l'ecosistema i no generin impactes negatius. Les necessitats de consumir aigua estan lligades al sector i a la ubicació de la planta. És important destacar que les empreses amb operacions en zones amb estrès hídric caldrà que avaluïn com fer una gestió sostenible dels recursos hídrics. Això inclou reduir el consum d'aigua, millorar la captura i reutilització de les aigües grises i millorar el tractament d'aigües residuals, entre d'altres. | E4: =HLOOKUP(E3,AUTO!$B$1:$AJ$2,2,FALSE) -> El subministrament de matèries primeres és un tema crucial per a la sostenibilitat d'aquells sectors molt intensius en materials. Aquí les empreses haurien d'avaluar oportunitats per a una adquisició de matèries de manera sostenible amb proveïdors confiables i certificats i estratègies de recuperació de material que es pugui recuperar com a matèria primera. Aquest tema pot ser important tant per a empreses que adquireixen matèries primeres com per a empreses que adquireixen prefabricats o productes. Un exemple és la cadena de subministrament d'empreses alimentàries, on és obligatori poder demostrar que el producte utilitzat no prové de zones amb alta deforestació. | F4: =HLOOKUP(F3,AUTO!$B$1:$AJ$2,2,FALSE) -> Les emissions de gasos amb efecte d'hivernacle i les energies renovables són categories estretament vinculades amb el canvi climàtic. Les empreses amb una major petjada de carboni contribueixen en major mesura al canvi climàtic. Reduir els impactes relacionats amb aquest tema requereix una reducció de la petjada de carboni de l'empresa. Això requereix una transició envers fonts d'energia renovables i la implementació d'estratègies per assolir emissions netes zero. | G4: =HLOOKUP(G3,AUTO!$B$1:$AJ$2,2,FALSE) -> Les emissions de contaminants com el diòxid de sofre (SOx), el diòxid de nitrogen (NOx) i els Compostos Orgànics Volàtils (VOC), entre d'altres, poden tenir un impacte significatiu sobre la qualitat de l'aire. Una mala qualitat de l'aire pot tenir efectes negatius tant sobre el medi ambient com sobre la salut de les comunitats afectades. Per tant, les empreses que duen a terme operacions que produeixen emissions a l'aire han d'avaluar el seu impacte sobre la qualitat de l'aire mitjançant controls regulars duts a terme per l'autoritat ambiental competent. Les empreses podrien considerar la instal·lació de filtres i altres mesures destinades a reduir les emissions de contaminants atmosfèrics. | H4: =HLOOKUP(H3,AUTO!$B$1:$AJ$2,2,FALSE) -> El disseny dels productes i els seus cicles de vida són molt importants per gestionar l'impacte mediambiental de l'empresa. L'ecodisseny pot facilitar la reparació i el manteniment del producte i millorar-ne la tria dels materials més adequats i la reuitilització. Un correcte ecodisseny assegura una reducció dels impactes en tot el cicle de vida del producte. Les empreses que tenen en compte els impactes durant tot el cicle de vida permeten reduir l'impacte total del producte o servei en l'ús de materials, disseny industrial, producció i gestió de residus. D'aquesta manera, les empreses s'adapten als esquemes de responsabilitat ampliada del productor o futures normatives enfocades a la circularitat de l'economia. | I4: =HLOOKUP(I3,AUTO!$B$1:$AJ$2,2,FALSE) -> L'eficiència energètica i les energies renovables se centren a disminuir el consum energètic respecte de la producció. Les empreses amb una alta eficiència energètica són més sostenibles ambientalment i econòmicament, ja que requereixen menys recursos (combustibles, electricitat, matèries primeres, etc.) per generar el mateix volum d'ingressos que una de menys eficient. | J4: =HLOOKUP(J3,AUTO!$B$1:$AJ$2,2,FALSE) -> Garantir la seguretat química és de gran importància per preservar els ecosistemes i protegir les comunitats properes a instal·lacions que empren substàncies químiques perilloses. Les empreses que comercialitzen productes que contenen substàncies químiques perilloses susceptibles d'entrar en contacte amb l'entorn natural o els usuaris d'aquests productes és essencial que prenguin totes les mesures necessàries per prevenir aquesta situació. Millorar la seguretat química pot implicar la recerca d'alternatives de materials per a l'ús en els seus productes, dissenyar productes de manera segura per prevenir fuites de substàncies i elaborar un pla de gestió de residus al final del cicle de vida del producte.
B5: Indicadors | D5: - Petjada hídrica total + Cadena de subministrament + Operacions directes + Distribució - Consum total d'aigua - Consum d'aigua per volum de negocis (€) - Consum d'aigua per producte (nombre o pes) - Consum d'aigua en àrees d'estrès hídric - Descàrrega total d'aigua - Descàrrega total d'aigua en àrees d'estrès hídric - % de reutilització de l'aigua | E5: - % de materials adquirits amb certificació de sostenibilitat - % dels principals proveïdors auditats en temes de sostenibilitat - Proves que els materials no provenen de zones recentment deforestades - Emissions de CO2 per kg de material (abast 3) - Consum d'aigua per kg o litre de material - Hectàrea de conversió de la terra (per exemple, deforestació) | F5: - Petjada de carboni de l'empresa (abast 1, 2 i 3), incloent: + emissions relacionades amb combustibles fòssils + emissions relacionades amb l'electricitat i el vapor adquirit + emissions de gasos refrigerants + Altres emissions vinculades amb els materials usats, viatges per a negocis, etc. - Capacitat per generar energia renovable - Canvis d'emissions i capacitat de renovables | G5: - Emissions SOx, NOx i Compostos Orgànics Volàtils (VOC) - Qualitat de l'aire interior - Emissions de NOx dels vehicles de transport a les ciutats | H5: - Emissions de GEH en tot el cicle de vida del producte - Necessitat de materials per a tot el cicle de vida del producte - % de productes dissenyats segons principis d'ecodisseny - Facilitat de reparació i manteniment del producte - Modularitat del producte - Compatibilitat del producte amb components d'altres marques o generals - Reciclabilitat del producte - % de productes amb programa de retorn (take back) | I5: - Consum energètic per unitat produïda - Consum energètic per € de vendes - Reducció d'emissions de CO2 - Taxa de conversió d'energia (eficiència per procés) - Hores d'operació dels equips - Consum energètic per tipus de font - Ràtio d'energia recuperada - Percentatge de millora en eficiència energètica | J5: - % dels materials que compleixen la legislació vigent i/o certificacions de sostenibilitat - % dels ingredients de fonts orgàniques - Reducció en l'ús de (agro)químics en la cadena de valor - Ús total (pes o volum) de químics identificats en els processos de producció - Reducció en l'ús de químics identificats en els processos de producció - % del personal que treballa amb químics que tenen la formació adequada - % de recuperació dels químics utilitzats en processos - Emissions de substàncies danyoses a l'aigua, aire o sòl
C6: Social | D6: Estàndards de treball en la cadena de valor | E6: Condicions laborals | F6: Salut i seguretat laboral | G6: Practiques de venda i etiquetatge
B7: Descripció | D7: =HLOOKUP(D6,AUTO!$B$1:$AJ$2,2,FALSE) -> És crucial mantenir alts estàndards laborals i condicions de treball dignes per a tots els empleats en la cadena de valor. L'empresa s'ha d'assegurar que tots els seus proveïdors respectin els drets laborals i humans, la qual cosa inclou garantir una remuneració justa, horaris laborals adequats i la prohibició del treball forçós i el treball infantil. Per assegurar condicions laborals acceptables en tota la cadena de valor, l'empresa pot requerir el compliment d'un codi de conducta per part dels seus proveïdors i dur a terme auditories en alguns d'ells per verificar-ne el compliment. | E7: =HLOOKUP(E6,AUTO!$B$1:$AJ$2,2,FALSE) -> Per tenir una bona consideració social i contribuir a una societat més justa, les empreses haurien d'oferir bones condicions laborals als seus empleats. Això no es limita al compliment dels drets humans; també inclou drets laborals, remuneració justa, horaris dignes, pagament d'hores extres, etc. Addicionalment, per anar més enllà dels compliments legals, les empreses poden oferir oportunitats de creixement, dret a desconnexió digital, posicions híbrides o en remot i altres mesures de conciliació per promoure l'equilibri entre la vida laboral i la personal. | F7: =HLOOKUP(F6,AUTO!$B$1:$AJ$2,2,FALSE) -> La salut i seguretat laboral hauria de ser una prioritat fonamental en qualsevol empresa. Totes les empreses han d'assegurar-se de proporcionar un entorn de treball segur i saludable per als seus empleats. Això és especialment crucial en aquelles empreses que duen a terme operacions perilloses o tenen el potencial d'afectar adversament la salut dels seus treballadors. Una de les mesures clau per assegurar la salut i seguretat dels empleats és designar un/a responsable de salut i seguretat la funció principal del qual consisteix a avaluar els riscos per als empleats i implementar mesures de mitigació corresponents. | G7: =HLOOKUP(G6,AUTO!$B$1:$AJ$2,2,FALSE) -> És essencial mantenir Bones Pràctiques en la venda i l'etiquetatge de productes per prevenir qualsevol pràctica enganyosa. Les pràctiques enganyoses poden portar els consumidors a triar un producte que no s'ajusti a les seves necessitats o requeriments. Per tant, per garantir Bones Pràctiques en la venda i l'etiquetatge, una empresa ha de gestionar la transparència de la informació relacionada amb els seus productes, operacions i cadenes de valor. A més, és fonamental proporcionar informació precisa i rellevant sobre els productes, sense ocultar desavantatges o altres tipus d'informació d'interès.
B8: Indicadors | D8: - % de compliment de proveïdors de les normatives laborals - Mitjana i màxim d'hores treballades per setmana - Índexs de salut i seguretat laboral dels provedors - % de provedors que recompensen hores extraordinàries - % d'empleats en contractes formals - Proveïdors certificats socialment (% valor dels contractes) - Participació dels proveïdors en iniciatives de responsabilitat social - Nombre de proveïdors auditats per condicions laborals | E8: - Compliment de les normatives laborals vigents - Hores de mitjana i màximes de la jornada laboral - Remuneració mitjana per posició, sexe i edat - Remuneració mitjana comparada amb costos de vida - % d'empleats coberts per convenis col·lectius - Disponibilitat de treball híbrid o remot (depèn de la posició) - Compensació de les hores extraordinàries - Període de llicència per paternitat / maternitat | F8: - Taxa d'accidentabilitat (per x empleats o per x hores treballades) - Índex de freqüència d'accidents (i canvis respecte d'altres anys) - Índex de gravetat d'accidents - Taxa de malalties laborals - Participació en formacions de seguretat - Taxa de compliment dels procediments de seguretat - Nombre d'inspeccions de seguretat realitzades - Freqüència d'avaluació dels riscos laborals | G8: - % dels productes en venda que compleixen la legislació d'etiquetes - Nombre de denúncies de pràctiques de publicitat, venda o etiquetatge enganyosos - Nombre d' instàncies on l'empresa ha hagut d'adaptar la publicitat d'un producte per informació falsa
C9: Governança | D9: Bon govern | E9: Gestió de la cadena de subministrament
B10: Descripció | D10: =HLOOKUP(D9,AUTO!$B$1:$AJ$2,2,FALSE) -> El bon govern és un tema ampli, enfocat en la gestió responsable i ètica de l'organització en general. L'acompliment de bon govern està vinculat als codis ètics de l'empresa, l'estructura de la propietat i el control de l'empresa, la junta directiva (i la seva remuneració), una comptabilitat transparent, la política fiscal i la transparència. | E10: =HLOOKUP(E9,AUTO!$B$1:$AJ$2,2,FALSE) -> La gestió de les cadenes de subministrament és essencial per supervisar les externalitats ambientals i socials generades per les activitats dels proveïdors. Dins de les cadenes de valor, poden sorgir problemes relacionats amb la responsabilitat ambiental, els drets humans, les condicions laborals, l'ètica i la corrupció, entre altres aspectes. La gestió de les cadenes de subministrament pot implicar l'avaluació, selecció, seguiment i compromís amb els proveïdors amb l'objectiu de reduir i mitigar els impactes mediambientals i socials.
B11: Indicadors | D11: - Composició de la junta directiva - % de membres independents dins la junta directiva - Existència de canals de denúncies i protecció de les parts interessades involucrades - % de denúncies investigades - Compliment de codis (ètic, conducta, etc.) i normatives - % dels empleats (incloent-hi junta directiva) amb remuneració basada en acompliment de sostenibilitat - Auditories i certificacions independents | E11: - % de proveïdors principals (valor de contractes) avaluats en temes de sostenibilitat - Petjada de carboni de la cadena de subministrament - % d'energia renovable en la cadena de subministrament - Reducció de residus i reciclatge dins de la cadena de subministrament (ecodisseny, embalatge, programes de retorn) - Certificació ambiental i social de proveïdors - Compliment dels drets laborals - Taxa d'accidentabilitat (per x empleats o per x hores treballades) - Seguretat de l'entorn laboral
B13: Mesures de gestió generals
B14: Tema | C14: Aplica a | D14: Descripció | E14: Fonts
B15: Bon govern - conducta de negocis | C15: Totes | D15: Comptar amb un codi de conducta que estableix normes per a tots els empleats. Aquest document s'haurà d'alinear amb les normatives vigents per al sector, incloent especialment temes ambientals (contaminació de l'aire, aigua i sòl, impactes en biodiversitat, emissions de GEH, etc.), drets humans, condicions laborals, seguretat, anticorrupció i suborn, promoció de la igualtat (de gènere) i la inclusió de tothom. | E15: Consulteu més informació sobre el codi de conducta
B16: Bon govern - control de qualitat | C16: Totes | D16: L'empresa ha d'establir un sistema de gestió i control de qualitat per a tots els serveis i productes oferts a fi d'assegurar la qualitat del producte i la seguretat per als clients. És una bona pràctica certificar aquest sistema de gestió amb un ISO9001. | E16: Vegeu informació sobre la ISO 9001
B17: Medi ambient - emissions de GEH | C17: Totes | D17: Calcular la petjada de carboni i adoptar fonts d'energia renovable beneficia les empreses de diverses maneres. Avaluar la petjada de carboni demostra un compromís ambiental sòlid, cosa que enforteix la reputació de l'empresa i atrau clients que valoren la sostenibilitat. La instal·lació de fonts d'energia renovable, com ara panells solars, no només redueix els costos a llarg termini, sinó que també disminueix la dependència envers els combustibles fòssils, cosa que al seu torn ajuda a mitigar l'impacte ambiental. A més d' aquests beneficis, complir objectius d'energia sostenible pot generar incentius fiscals i subvencions que milloren la rendibilitat de l'empresa. Aquestes accions no només aporten beneficis econòmics i ambientals, sinó que també reforcen la responsabilitat social de l'empresa i la posicionen com a líder en pràctiques empresarials sostenibles. | E17: Consulteu informació sobre el GHG Protocol
B18: Impactes ambientals - sistema de gestió ambiental | C18: Totes | D18: L'empresa ha d'establir un sistema de gestió mediambiental que permeti identificar i avaluar els impactes potencials i reals, els riscos i les oportunitats relacionats amb la sostenibilitat de l' empresa. Els marcs per desenvolupar un sistema de gestió mediambiental són l'EMAS de la Unió Europea i la ISO14001. | E18: Consulteu informació sobre EMAS
E19: Vegeu informació sobre la ISO 14001
B20: General - estat d'informe no financer | C20: Totes | D20: Els requisits de divulgació d'informació no financera, especialment pel que fa a la sostenibilitat, estan guanyant rellevància tant per a inversors com per a organismes públics. Aquesta tendència es troba estretament vinculada amb les regulacions de la Unió Europea en el marc del Pla de finances sostenibles i el Pacte verd. Tant la Directiva d'informació empresarial sostenible (CSRD) com la Llei 11/2018 harmonitzen els requisits de divulgació per a les grans empreses. Aquestes i altres iniciatives estan generant un efecte dominó sobre les cadenes de valor i el sistema financer, la qual cosa està portant a una major demanda d'informació per part d'empreses de totes les mides. Per tant, la divulgació d'informació sobre sostenibilitat reforça la posició d'una empresa en el mercat. Per a les petites i mitjanes empreses (PIME) que volen començar a divulgar informació no financera, el marc de referència GRI pot servir com a base. | E20: Consulteu més informació sobre la CSRD
E21: Consulteu la Llei 11/2018
E22: Consulteu més informació sobre el marc GRI
B23: Medi ambient - eficiència energètica | C23: Totes | D23: L'eficiència energètica exerceix un paper fonamental en la reducció de les emissions de gasos amb efecte d'hivernacle de qualsevol empresa. Millorar l'eficiència energètica permet a una empresa generar valor amb un menor ús de recursos escassos. El document BREF de la Unió Europea proporciona orientació específica per assolir un ús eficient dels recursos i l'energia en diversos sectors i promou l'adopció de pràctiques sostenibles i alineades amb els objectius de la UE. Això no només beneficia la sostenibilitat econòmica de l'empresa, sinó que també contribueix a combatre el canvi climàtic. | E23: Consulteu el Document de referència sobre les millors tecnologies disponibles en termes d'eficiència energètica
B24: Protecció de dades - política de protecció de dades | C24: Totes | D24: L'empresa ha d'establir una política de protecció de dades alineada amb la Llei de protecció de dades de la UE. Tot el personal ha de rebre formació per gestionar dades del client de manera adequada i hi ha d'haver un protocol de contingència per a casos d' emergència. Adjunt a la columna de fonts trobareu un exemple d'una política de protecció de dades de l'Agència Catalana de Turisme. | E24: Consulteu un exemple d'una política de protecció de dades
B25: Bon govern - conducta de proveïdors | C25: Totes | D25: L'empresa ha d'establir un codi de conducta per als seus proveïdors i altres actors en la cadena de valor del negoci. Aquest codi ha de ser signat pels proveïdors i exigir-ne el compliment amb els estàndards de bon govern establerts en el document. Es recomana alinear aquest codi de conducta amb el codi de conducta intern, encara que en certs casos es pot permetre certa flexibilitat, sempre que continuï estant conforme amb les regulacions vigents relacionades amb la cadena de valor com ara aquelles relacionades amb la no deforestació, els drets humans o les emissions de carboni, entre d'altres. A la columna 'Fonts' adjunta, trobareu un exemple d'un codi de conducta/ètic per a proveïdors del Pacte Mundial de Nacions Unides. | E25: Consulteu un exemple de codi de conducta/ètic de proveïdors
B26: Social - Pla d'igualtat de gènere | C26: Empreses amb més de 50 treballadors | D26: L'empresa ha d'implementar un pla d'igualtat de gènere en compliment del Reial decret 901/2020. Aquest requisit implica que les empreses han d'adoptar, amb negociació prèvia, mesures destinades a prevenir qualsevol forma de discriminació laboral entre dones i homes i a fomentar condicions de treball que evitin l'assetjament sexual i l'assetjament per raó de gènere. A més, han d'establir procediments específics per a la prevenció d'aquests comportaments i per gestionar les denúncies o reclamacions presentades per qui n'hagi estat víctima. | E26: Consulteu el Reial decret 901/2020
B27: Medi ambient - residus | C27: Totes | D27: A partir de l'1 de gener de 2023, va entrar en vigor la Llei 7/2022, de 8 d'abril, de residus i sòls contaminats per una economia circular, que amplia la responsabilitat del productor de residus fins que aquests residus hagin estat gestionats per un gestor final. Això té implicacions per a totes les empreses que generen residus, ja que s'han d'assegurar que els residus siguin tractats o eliminats de manera adequada. A més, la llei estableix que el productor de residus ha de fer separacions mínimes o garantir que un gestor les realitzi. També se li exigeix prioritzar la prevenció de la generació de residus per sobre de la reutilització, i aquesta per sobre del reciclatge, i aquest últim per sobre de l'eliminació. Finalment, s'ha de donar prioritat als gestors ubicats geogràficament a prop. L'Agència de Residus de Catalunya té competència sobre els residus que es generen a Catalunya i els que es gestionen al seu àmbit territorial. Queden exclosos de la seva competència els residus radioactius, els residus resultants de la prospecció, l’extracció, el tractament i l’emmagatzematge de recursos minerals i de l’explotació de pedreres, els residus d’explotacions agrícoles i ramaderes que no siguin perillosos i s’utilitzin exclusivament en el marc de l’explotació agrària, els explosius desclassificats, les aigües residuals i els efluents gasosos emesos a l’atmosfera. | E27: Consulteu la Llei 7/2022
E28: Consulteu informació en normativa catalana en matèria de residus
B29: Medi ambient - materials d'embalatge | C29: Totes | D29: Atès que la indústria manufacturera produeix productes físics, els materials d'embalatge utilitzats per al transport i la distribució d' aquests productes són un factor crucial amb un impacte potencialment significatiu. Per aquesta raó, la Unió Europea ha implementat una nova legislació que requereix la reducció de l'ús de plàstics d'un sol ús i en prohibeix certes aplicacions. A més, des de l'1 de gener, va entrar en vigor la Llei 7/2022, que estableix un nou impost sobre els envasos de plàstic no reutilitzables. Per tant, és important cercar materials d'embalatge que generin un menor impacte sobre el medi ambient adaptats a l'aplicació i la ubicació geogràfica dels productes. La 'Sustainable Packaging Coalition' ofereix diverses iniciatives destinades a ajudar les empreses a reduir l'impacte ambiental dels seus envasos. | E29: Consulteu informació sobre la Sustainable Packaging Coalition
E30: Consulteu informació sobre la Llei de plàstics d'un sol ús
E31: Consulteu informació sobre impostos sobre els envasos de plàstic no reutilitzables
B32: Medi ambient - Emissions de carboni | C32: Totes | D32: El transport de materials i productes contribueix al canvi climàtic a causa de les emissions de carboni que genera. Si bé és possible reduir la petjada de carboni en les activitats mateixes mitjançant l'ús d'energies renovables, el transport en si també té un impacte significatiu. Per aquesta raó, és important considerar formes de transport sostenible, com ara mitjans de transport respectuosos envers el medi ambient o la selecció de proveïdors locals, entre altres mesures. En el sector de la logística, hi ha iniciatives destinades a reduir les emissions d'aquest sector. Un exemple d'aquestes iniciatives és Lean and Green, que ajuda les empreses logístiques a reduir les seves emissions i compta amb un sistema de classificació basat en el seu acompliment. | E32: Consulteu informació sobre la iniciativa Lean and Green
E33: Consulteu informació sobre l'Oficina Catalana de Canvi Climàtic
B34: Medi ambient - compra sostenible | C34: Totes | D34: És important avaluar la sostenibilitat dels possibles proveïdors i donar prioritat a aquells que tenen el millor acompliment en aspectes ambientals, socials i de governança (ESG). Per garantir la compra sostenible, les empreses poden establir una política de compra sostenible per a tots els seus proveïdors, avaluar i prioritzar els proveïdors segons el seu acompliment en ASG i certificacions de sostenibilitat de productes, com l'EU Ecolabel, i col·laborar per assegurar una millora contínua, entre altres mesures. Actualment, la Unió Europea està desenvolupant legislació per exigir a les grans empreses que garanteixin la sostenibilitat en les seves compres, en forma del CSDDD (Corporate Sustainable Due Diligence Directive proposal). | E34: Vegeu la ISO 20400:2017 sobre compra sostenible
E35: Consulteu informació sobre l'EU Ecolabel
B36: Social - Estratègia Catalana de Seguretat i Salut Laboral | C36: Totes | D36: L’Estratègia catalana de seguretat i salut laboral 2021-2026 té com a objectiu millorar les condicions de treball a Catalunya, reduir la sinistralitat laboral i promoure la prevenció de riscos laborals. És fruit del treball conjunt entre la Generalitat, patronals i sindicats, amb indicadors per avaluar-ne el progrés i una perspectiva de gènere transversal. | E36: Consulta informació sobre l'Estratègia Catalana de Seguretat i Salut Laboral
B37: Bon govern - Pla de govern de la Generalitat de Catalunya | C37: Totes | D37: Aquest Pla contempla un eix dedicat a la "Transformació Democràtica", que inclou aspectes com el "Bon govern i govern obert". Aquest enfocament pot ser rellevant per al sector, ja que promou la transparència, l'ètica i la responsabilitat en les pràctiques de govern, que poden ser aplicades o servir d'exemple per a les empreses del sector​. | E37: Consulta informació sobre el Pla de govern de la Generalitat de Catalunya
B38: Resiliència del model de negoci - Estratègia RIS3CAT 2030, per a l'especialització intel·ligent de Catalunya | C38: Totes | D38: L’Estratègia RIS3CAT 2030, encara que no està enfocada específicament envers aquest sector, pot enfortir la resiliència dels models de negoci de les seves empreses PIME. Això s’aconsegueix mitjançant el foment de la innovació i la col·laboració intersectorial, la diversificació de serveis, la capacitació i el desenvolupament de talent, i també proporcionant accés a recursos i xarxes de suport. Aquestes accions poden ajudar les empreses de serveis professionals a adaptar-se i créixer en un entorn empresarial dinàmic. | E38: Consulta informació sobre Estratègia RIS3CAT 2030
B41: Temes específics per a la indústria de la moda i el tèxtil
B42: Tema | C42: Aplica a | D42: Descripció | E42: Font
B43: Medi ambient - moda circular | C43: Totes | D43: Catalunya històricament s’ha caracteritzat per disposar d’una potent indústria tèxtil. Actualment, destaca dins d’Europa pel seu gran potencial d’aprofitament dels residus tèxtils. El Pacte per a la moda circular a Catalunya impulsa la transformació del sector del tèxtil envers un model circular a partir d’una perspectiva integral i integradora de tots els actors de la seva cadena de valor. El Pacte per a la moda circular és un pacte voluntari entre institucions i empreses de les diferents baules de la cadena de valor tèxtil de Catalunya que facilitarà la incorporació de mesures de circularitat, l’impuls de projectes col·laboratius i la millora de la competitivitat del sector. | E43: Pacte per a la moda circular
B44: Diversos - Etiqueta ecològica UE | C44: Totes | D44: Per fomentar l'oferta de productes sostenibles dins la Unió Europea, hi ha l'Ecoetiqueta. Aquesta etiqueta assenyala als consumidors que el producte compleix uns criteris de sostenibilitat exigents de la Unió Europea. Aquests criteris inclouen temes com ara: compliment de normes laborals bàsiques, condicions laborals, sostenibilitat de materials, gestió sostenible de l'aigua, seguretat química i eficiència energètica. | E44: Consulteu els requisits de l'Ecoetiqueta UE - vestimenta i roba
B45: Diversos - estàndard global de reciclatge | C45: Totes | D45: El Global Recycling Standard és un marc important per als actors del sector que cerquen establir un nivell de sostenibilitat dins de la seva cadena de valor. Diverses empreses exigeixen complir el Global Recycling Standard per assegurar estàndards mínims de sostenibilitat, socials i de bon govern. Els temes ambientals se centren en emissions de GEH, eficiència energètica, gestió de residus, circularitat, gestió sostenible de l'aigua i sistemes de gestió ambiental, entre d'altres. Els temes socials del Global Recycling Standard s'enfoquen a establir bones condicions laborals, respectar els drets humans al llarg de la cadena de valor i ser un ocupador inclusiu. | E45: Consulteu el Global Recycling Standard
B46: Diversos: Certificat de comerç just | C46: Totes | D46: Originalment, la certificació Fairtrade se centrava principalment en aspectes socials amb l'objectiu de defensar els drets dels treballadors en la cadena de valor. Alguns dels temes socials incorporats en la certificació Fairtrade són antidiscriminació, protecció de nens, condicions laborals (incloent-hi retribució justa i hores limitades) i seguretat laboral. Avui, la certificació Fairtrade també inclou temes ambientals; per al sector de tèxtil, això inclou aigües residuals, gestió de químics, emissions i consum energètic, entre d'altres. Addicionalment, advoquen per la traçabilitat en la cadena de valor i pràctiques de negocis responsables. | E46: Consulteu informació sobre tèxtils Fairtrade
B47: Diversos - estàndard tèxtil orgànic global (GOTS) | C47: Totes | D47: El Global Organic Textile Standard té com a objectiu establir una definició uniforme de tèxtils orgànics dins del mercat. Els estàndards defineixen els materials permesos dins de productes tèxtils organics i els requisits per a l'ús de químics. Addicionalment, estableixen requisits socials per combatre el treball forçós, el treball infantil i la discriminació. Addicionalment, promouen la gestió sostenible dels residus, l'equitat de gènere, la seguretat i les condicions laborals (incloent-hi remuneració justa i hores laborals). | E47: Consulteu l'estàndard de Global Organic Tèxtils
B48: Medi ambient - seguretat química, entre d'altres: OEKO TEX | C48: Totes | D48: OEKO-TEX és una etiqueta per a la indústria de tèxtils i cuir que indica l'absència de substàncies danyoses per a la salut de l'usuari del producte. OEKO-TEX té una varietat de tipus d'estàndards, tant per a tèxtils com per a cuir. Els estàndards OEKO-TEX inclouen controls per a substàncies perilloses regulades i no regulades. Aquest estàndard permet assenyalar als consumidors que el producte no conté substàncies perilloses i dona suport a reclams sobre la qualitat dels productes. | E48: Consulteu els requisits d'OEKO-TEX
B49: Diversos - millors tecnologies disponibles | C49: Totes | D49: En la indústria tèxtil, l'adopció de les millors tecnologies disponibles en línia amb els documents BREF és crucial per potenciar l'acompliment de sostenibilitat. Aquestes tecnologies avançades optimitzen la producció, redueixen l'ús de recursos naturals i disminueixen la generació de residus i emissions. En seguir les directrius dels documents BREF, les empreses tèxtils poden millorar la seva eficiència i responsabilitat ambiental i s'alineen amb estàndards reconeguts a escala europea. A més, la implementació d'aquestes pràctiques sostenibles millora la reputació de l' empresa en respondre a la creixent demanda de consumidors conscients i ètics. En sintonia amb això, l'adopció de tecnologies recolzades pels documents BREF impulsa la competitivitat, la sostenibilitat i la imatge de marca en la indústria tèxtil. | E49: Consulteu el document BREF sobre les millors tecnologies disponibles en la indústria tèxtil
B50: Medi ambient - circularitat | C50: Totes | D50: Per a productes físics, els impactes més significatius sovint estan relacionats amb els materials necessaris per a la producció i els residus generats al final de la seva vida útil. Per reduir aquests impactes, hi ha diverses iniciatives que promouen la reutilització, la recuperació i el reciclatge de materials. La Unió Europea ha desenvolupat un pla d'acció per fomentar l'economia circular i reduir l'eliminació de residus. A més, diverses ONG i indústries han implementat iniciatives per millorar la circularitat dels productes i els processos de producció. En aquest context, l'ecodisseny o disseny per a la circularitat exerceix un paper fonamental, ja que el disseny d'un producte influeix en gran mesura en la seva capacitat de ser posteriorment reciclat. Catalunya Circular és el hub d’innovació i punt de trobada d’empreses i institucions que aporten solucions i estratègies per consolidar l’economia circular a Catalunya. La certificació Cradle to Cradle s'atorga a productes que compleixen els principis de l'economia circular, i la Fundació Ellen MacArthur difon informació sobre l'economia circular i com implementar-la. | E50: Consulta informació sobre Catalunya Circular, l'Observatori d'economia circular
E51: Consulteu més informació sobre l'economia circular (Fundació Ellen McArthur)
E52: Consulteu més informació sobre el certificat Cradle to Cradle
E53: Consulteu informació sobre la Sustainable Packaging Coalition
B54: Social - Conveni col·lectiu de treball del sector del comerç tèxtil de la província de Barcelona per als anys 2022-2024 | C54: Totes | D54: El Conveni col·lectiu de treball del sector del comerç tèxtil de la província de Barcelona per als anys 2022-2024 estableix les condicions laborals i els drets dels treballadors en aquest sector durant aquest període. Inclou aspectes com ara salaris, jornada laboral, vacances i altres beneficis laborals amb l’objectiu de regular les relacions laborals i millorar les condicions dels empleats en aquest àmbit. | E54: Consulta informació sobre el Conveni Col·lectiu de Treball del Sector del Comerç Tèxtil de la Província de Barcelona per als anys 2022-2024

Sheet Fusta i Paper
D1: Indústria de fusta i paper | E1: Aquesta indústria és una agrupació dels CNAE 16 i 17, la indústria de fusta i suro, i la de paper. Aquests sectors ofereixen productes on la gestió sostenible de les matèries primeres és clau. Així mateix, els processos de producció poden requerir molta energia i aigua, cosa que fa que una revisió holística del cicle de vida sigui indispensable.
D3: Gestió sostenible de l'aigua | E3: Biodiversitat i Ecosistemes | F3: Emissions de GEH | G3: Eficiència energètica i energies renovables | H3: Qualitat de l'Aire | I3: Disseny del producte i gestió del cicle de vida | J3: Subministrament de matèries primeres / Productes venuts | K3: Gestió de Residus i Materials Perillosos
B4: Descripció | C4: Medi ambient | D4: =HLOOKUP(D3,AUTO!$B$1:$AJ$2,2,FALSE) -> La gestió sostenible de l'aigua tracta d'assegurar que el consum i ús d'aquesta aigua per part de l'empresa estiguin alineats amb la capacitat de recuperar-se de l'ecosistema i no generin impactes negatius. Les necessitats de consumir aigua estan lligades al sector i a la ubicació de la planta. És important destacar que les empreses amb operacions en zones amb estrès hídric caldrà que avaluïn com fer una gestió sostenible dels recursos hídrics. Això inclou reduir el consum d'aigua, millorar la captura i reutilització de les aigües grises i millorar el tractament d'aigües residuals, entre d'altres. | E4: =HLOOKUP(E3,AUTO!$B$1:$AJ$2,2,FALSE) -> Aquesta categoria se centra en els impactes de les operacions o els actius d'una empresa sobre ecosistemes i la seva biodiversitat. Les activitats amb potencials impactes significatius són aquelles vinculades amb canvis en l'ús del sòl per a exploració/explotació de recursos naturals, construcció, agricultura extensiva, etc. Els impactes poden produir pèrdua de biodiversitat, destrucció d'hàbitats, deforestació i pèrdua de serveis ecosistèmics bàsics. Les empreses haurien d'avaluar les seves dependències i impactes sobre el capital natural (natura), mitigar els riscos associats i fomentar un impacte positiu en totes les fases de la cadena de valor de l'empresa. | F4: =HLOOKUP(F3,AUTO!$B$1:$AJ$2,2,FALSE) -> Les emissions de gasos amb efecte d'hivernacle i les energies renovables són categories estretament vinculades amb el canvi climàtic. Les empreses amb una major petjada de carboni contribueixen en major mesura al canvi climàtic. Reduir els impactes relacionats amb aquest tema requereix una reducció de la petjada de carboni de l'empresa. Això requereix una transició envers fonts d'energia renovables i la implementació d'estratègies per assolir emissions netes zero. | G4: =HLOOKUP(G3,AUTO!$B$1:$AJ$2,2,FALSE) -> L'eficiència energètica i les energies renovables se centren a disminuir el consum energètic respecte de la producció. Les empreses amb una alta eficiència energètica són més sostenibles ambientalment i econòmicament, ja que requereixen menys recursos (combustibles, electricitat, matèries primeres, etc.) per generar el mateix volum d'ingressos que una de menys eficient. | H4: =HLOOKUP(H3,AUTO!$B$1:$AJ$2,2,FALSE) -> Les emissions de contaminants com el diòxid de sofre (SOx), el diòxid de nitrogen (NOx) i els Compostos Orgànics Volàtils (VOC), entre d'altres, poden tenir un impacte significatiu sobre la qualitat de l'aire. Una mala qualitat de l'aire pot tenir efectes negatius tant sobre el medi ambient com sobre la salut de les comunitats afectades. Per tant, les empreses que duen a terme operacions que produeixen emissions a l'aire han d'avaluar el seu impacte sobre la qualitat de l'aire mitjançant controls regulars duts a terme per l'autoritat ambiental competent. Les empreses podrien considerar la instal·lació de filtres i altres mesures destinades a reduir les emissions de contaminants atmosfèrics. | I4: =HLOOKUP(I3,AUTO!$B$1:$AJ$2,2,FALSE) -> El disseny dels productes i els seus cicles de vida són molt importants per gestionar l'impacte mediambiental de l'empresa. L'ecodisseny pot facilitar la reparació i el manteniment del producte i millorar-ne la tria dels materials més adequats i la reuitilització. Un correcte ecodisseny assegura una reducció dels impactes en tot el cicle de vida del producte. Les empreses que tenen en compte els impactes durant tot el cicle de vida permeten reduir l'impacte total del producte o servei en l'ús de materials, disseny industrial, producció i gestió de residus. D'aquesta manera, les empreses s'adapten als esquemes de responsabilitat ampliada del productor o futures normatives enfocades a la circularitat de l'economia. | J4: =HLOOKUP(J3,AUTO!$B$1:$AJ$2,2,FALSE) -> El subministrament de matèries primeres és un tema crucial per a la sostenibilitat d'aquells sectors molt intensius en materials. Aquí les empreses haurien d'avaluar oportunitats per a una adquisició de matèries de manera sostenible amb proveïdors confiables i certificats i estratègies de recuperació de material que es pugui recuperar com a matèria primera. Aquest tema pot ser important tant per a empreses que adquireixen matèries primeres com per a empreses que adquireixen prefabricats o productes. Un exemple és la cadena de subministrament d'empreses alimentàries, on és obligatori poder demostrar que el producte utilitzat no prové de zones amb alta deforestació. | K4: =HLOOKUP(K3,AUTO!$B$1:$AJ$2,2,FALSE) -> La gestió de residus perillosos i no perillosos és un àmbit en constant evolució normativa. L'adequada gestió de residus i materials perillosos és clau per reduir la contaminació causada per l'empresa o els productes que posa al mercat. Optimitzar el disseny i la producció i treballar paral·lelament a millorar la gestió de residus és clau per transicionar envers una economia circular que redueixi la necessitat d'explotació de nous recursos naturals. Per tant, les empreses que gestionen els seus residus i eviten la seva generació són més sostenibles i estan més alineades amb els principis de l'economia circular.
B5: Indicadors | D5: - Petjada hídrica total + Cadena de subministrament + Operacions directes + Distribució - Consum total d'aigua - Consum d'aigua per volum de negocis (€) - Consum d'aigua per producte (nombre o pes) - Consum d'aigua en àrees d'estrès hídric - Descàrrega total d'aigua - Descàrrega total d'aigua en àrees d'estrès hídric - % de reutilització de l'aigua | E5: - Àrea de conversió dels ecosistemes (per exemple: deforestació o conversió de bosc verge a silvicultura) + Generat per les operacions mateixes + Generat per la cadena de valor - Abundància mitjana d'espècies - Canvis en l'abundància mitjana d'espècies | F5: - Petjada de carboni de l'empresa (abast 1, 2 i 3), incloent: + emissions relacionades amb combustibles fòssils + emissions relacionades amb l'electricitat i el vapor adquirit + emissions de gasos refrigerants + Altres emissions vinculades amb els materials usats, viatges per a negocis, etc. - Capacitat per generar energia renovable - Canvis d'emissions i capacitat de renovables - Captura de carboni (potencialment pels boscos mateixos) | G5: - Consum energètic per unitat o pes produït - Consum energètic per € de vendes - Reducció d'emissions de CO2 - Taxa de conversió d'energia (eficiència per procés) - Hores d'operació dels equips - Consum energètic per tipus de font - Ràtio d'energia recuperada - Percentatge de millora en eficiència energètica | H5: - Emissions SOx, NOx i Compostos Orgànics Volàtils (VOC) - Qualitat de l'aire interior - Emissions de NOx dels vehicles de transport a les ciutats - Contribució a l'aire net (potencialment pels boscos) | I5: - Emissions de GEH en tot el cicle de vida del producte - Necessitat de materials per a tot el cicle de vida del producte - % de productes dissenyat segons principis d'ecodisseny - Facilitat de reparació i manteniment del producte - Modularitat del producte - Compatibilitat del producte amb components d' altres marques o generals - Reciclabilitat del producte - % de productes amb programa de retorn (take-back) | J5: - % de materials adquirit amb certificació de sostenibilitat (gestió sostenible de boscos) - % dels principals proveïdors auditats en temes de sostenibilitat - Emissions de CO2 per kg de material (abast 3) - Consum d' aigua per kg o litre de material - Hectàrea de conversió de la terra (per exemple, deforestació) dins de la cadena de subministrament | K5: - Generació total de residus - Generació de residus perillosos - Generació de residus no perillosos - % de residus destinats a eliminació - % de residus destinats a reutilització o reciclatge - % de residus destinats a compostatge - % de productes dissenyats segons principis d'ecodisseny
C6: Social | D6: Salut i seguretat laboral | E6: Relacions amb les comunitats afectades
B7: Descripció | D7: =HLOOKUP(D6,AUTO!$B$1:$AJ$2,2,FALSE) -> La salut i seguretat laboral hauria de ser una prioritat fonamental en qualsevol empresa. Totes les empreses han d'assegurar-se de proporcionar un entorn de treball segur i saludable per als seus empleats. Això és especialment crucial en aquelles empreses que duen a terme operacions perilloses o tenen el potencial d'afectar adversament la salut dels seus treballadors. Una de les mesures clau per assegurar la salut i seguretat dels empleats és designar un/a responsable de salut i seguretat la funció principal del qual consisteix a avaluar els riscos per als empleats i implementar mesures de mitigació corresponents. | E7: =HLOOKUP(E6,AUTO!$B$1:$AJ$2,2,FALSE) -> Les organitzacions tenen un impacte sobre les comunitats on operen, tant a través d'impactes físics com a través de la interacció amb els membres d'aquestes comunitats que treballen a l'empresa. Per tant, és fonamental establir relacions sòlides i respectuoses envers les comunitats afectades a través d'un diàleg que permeti comprendre i abordar els impactes negatius generats per les operacions. Algunes eines que es poden utilitzar per mantenir relacions efectives amb les comunitats inclouen la realització de reunions periòdiques amb representants de la comunitat, la incorporació de membres de la societat a l'empresa i el manteniment d'una comunicació constant amb organitzacions locals.
B8: Indicadors | D8: - Taxa d'accidentalitat (per x empleats o per x hores treballades) - Índex de freqüència d'accidents (i canvis respecte d'altres anys) - Índex de gravetat d'accidents - Taxa de malalties laborals - Participació en formacions de seguretat - Taxa de compliment de procediments de seguretat - Nombre d'inspeccions de seguretat realitzades - Freqüència d'avaluació dels riscos laborals | E8: - Freqüència de sessions d'interacció amb els grups d'interès de l'empresa - Inversions en les comunitats afectades per l'empresa (infraestructura, escoles, centres de salut, etc.) - Nombre d'empleats de comunitats locals (especialment en comunitats marginalitzades)
C9: Governança | D9: Bon govern
B10: Descripció | D10: =HLOOKUP(D9,AUTO!$B$1:$AJ$2,2,FALSE) -> El bon govern és un tema ampli, enfocat en la gestió responsable i ètica de l'organització en general. L'acompliment de bon govern està vinculat als codis ètics de l'empresa, l'estructura de la propietat i el control de l'empresa, la junta directiva (i la seva remuneració), una comptabilitat transparent, la política fiscal i la transparència.
B11: Indicadors | D11: =HLOOKUP(D9,AUTO!$B$1:$AJ$3,3,FALSE) -> - Composició de la junta directiva - % de membres independents dins la junta directiva - Existència de canals de denúncies i protecció de les parts interessades involucrades - % d'alts càrrecs investigats o condemnats - Compliment de codis (ètic, conducta, etc.) i normatives - % dels empleats (incloent-hi junta directiva) amb remuneració basada en la consecució d'objectius de sostenibilitat. - Auditories i certificacions independents
B13: Mesures de gestió generals
B14: Tema | C14: Aplica a | D14: Descripció | E14: Fonts
B15: Bon govern - conducta de negocis | C15: Totes | D15: Comptar amb un codi de conducta que estableixi normes per a tots els empleats. Aquest document s'haurà d'alinear amb les normatives vigents per al sector, incloent especialment temes ambientals (contaminació de l'aire, aigua, sòl, impactes sobre la biodiversitat, emissions GEH, etc.), drets humans, condicions laborals, seguretat, anticorrupció i suborn, promoció de la igualtat (de gènere) i la inclusió de tothom. | E15: Consulteu més informació sobre el codi de conducta
B16: Bon govern - control de qualitat | C16: Totes | D16: L'empresa ha d'establir un sistema de gestió i control de qualitat per a tots els serveis i productes oferts a fi d'assegurar la qualitat del producte i la seguretat per als clients. És una bona pràctica certificar aquest sistema de gestió amb una ISO9001. | E16: Vegeu informació sobre la ISO 9001
B17: Impactes ambientals - sistema de gestió ambiental | C17: Totes | D17: L'empresa ha d'establir un sistema de gestió mediambiental que permeti identificar i avaluar els impactes potencials i reals i els riscos i les oportunitats relacionats amb la sostenibilitat de l'empresa. Els marcs per desenvolupar un sistema de gestió mediambiental són l'EMAS de la Unió Europea i la ISO14001. | E17: Consulta informació sobre EMAS
E18: Veure informació sobre ISO 14001.
B19: General - estat d'informe no financer | C19: Totes | D19: Els requisits de divulgació d'informació no financera, especialment pel que fa a la sostenibilitat, estan guanyant rellevància tant per a inversors com per a organismes públics. Aquesta tendència es troba estretament vinculada amb les regulacions de la Unió Europea en el marc del Pla de finances sostenibles i el Pacte verd. Tant la Directiva d'informació corporativa sostenible (CSRD) com la Llei 11/2018 harmonitzen els requisits de divulgació per a les grans empreses. Aquestes i altres iniciatives estan generant un efecte dominó sobre les cadenes de valor i el sistema financer, la qual cosa està portant a una major demanda d'informació per part d'empreses de totes les mides. Per tant, la divulgació d'informació sobre sostenibilitat reforça la posició d'una empresa en el mercat. Per a les petites i mitjanes empreses (PIME) que volen començar a divulgar informació no financera, el marc de referència GRI pot servir com a base. | E19: Consulteu més informació sobre la CSRD
E20: Consulteu la Llei 11/2018
E21: Consulteu més informació sobre el marc GRI
B22: Medi ambient - emissions de GEH | C22: Totes | D22: Calcular la petjada de carboni i adoptar fonts d'energia renovable beneficia les empreses de diverses maneres. Avaluar la petjada de carboni demostra un compromís ambiental sòlid, enforteix la reputació i atrau clients sensibles a la sostenibilitat. La instal·lació de fonts d'energia renovable, com ara panells solars, no només redueix els costos a llarg termini, sinó que també disminueix la dependència envers els combustibles fòssils, cosa que al seu torn ajuda a mitigar l'impacte ambiental. A més d'aquests beneficis, complir objectius d'energia sostenible pot generar incentius fiscals i subvencions que milloren la rendibilitat de l'empresa. Aquestes accions no només aporten beneficis econòmics i mediambientals, sinó que també reforcen la responsabilitat social de l'empresa i la posicionen com a líder en pràctiques empresarials sostenibles. | E22: Consulteu informació sobre el Protocol de GEH
B23: Medi ambient - eficiència energètica | C23: Totes | D23: L'eficiència energètica exerceix un paper fonamental en la reducció de les emissions de gasos amb efecte d'hivernacle de qualsevol empresa. Millorar l'eficiència energètica permet a una empresa generar valor amb un menor ús de recursos escassos. El document BREF de la Unió Europea proporciona orientació específica per assolir un ús eficient dels recursos i l'energia en diversos sectors i promou l'adopció de pràctiques sostenibles i alineades amb els objectius de la UE. Això no només beneficia la sostenibilitat econòmica de l'empresa, sinó que també contribueix a combatre el canvi climàtic. | E23: Consulteu el Document de referència sobre les millors tecnologies disponibles en termes d'eficiència energètica
B24: Protecció de dades - política de protecció de dades | C24: Totes | D24: L'empresa ha d'establir una política de protecció de dades, alineada amb la llei de protecció de dades de la UE. Tot el personal ha de rebre formació per gestionar dades del client de manera adequada i hi ha d'haver un protocol de contigència per a casos d'emergència. Adjunt a la columna de fonts trobareu un exemple d'una política de protecció de dades de l'Agència Catalana de Turisme. | E24: Consulteu un exemple d'una política de protecció de dades
B25: Bon govern - conducta de proveïdors | C25: Totes | D25: L'empresa ha d'establir un codi de conducta per als seus proveïdors i altres actors en la cadena de valor del negoci. Aquest codi ha de ser signat pels proveïdors i exigir-ne el compliment amb els estàndards de bon govern establerts en el document. Es recomana alinear aquest codi de conducta amb el codi de conducta intern, encara que en certs casos es pot permetre certa flexibilitat, sempre que continuï estant de conformitat amb les regulacions vigents relacionades amb la cadena de valor, com aquelles relacionades amb la no deforestació, els drets humans o les emissions de carboni, entre d'altres. A la columna 'Fonts' adjunta, trobareu un exemple d'un codi de conducta/ètic per a proveïdors del Pacte Mundial de Nacions Unides. | E25: Consulteu un exemple de codi de conducta/ètic de proveïdors
B26: Social - Pla d'igualtat de gènere | C26: Empreses amb més de 50 treballadors | D26: L'empresa ha d'implementar un pla d'igualtat de gènere en compliment del Reial decret 901/2020. Aquest requisit implica que les empreses han d'adoptar, amb negociació prèvia, mesures destinades a prevenir qualsevol forma de discriminació laboral entre dones i homes i a fomentar condicions de treball que evitin l'assetjament sexual i l'assetjament per raó de gènere. A més, han d'establir procediments específics per a la prevenció d'aquests comportaments i per gestionar les denúncies o reclamacions presentades per qui n'hagi estat víctima. | E26: Consulteu el Reial decret 901/2020
B27: Medi ambient - residus | C27: Totes | D27: A partir de l'1 de gener de 2023, va entrar en vigor la Llei 7/2022, de 8 d'abril, de residus i sòls contaminats per una economia circular, que amplia la responsabilitat del productor de residus fins que aquests residus hagin estat gestionats per un gestor final. Això té implicacions per a totes les empreses que generen residus, ja que s'han d'assegurar que els residus siguin tractats o eliminats de manera adequada. A més, la Llei estableix que el productor de residus ha de fer separacions mínimes o garantir que un gestor les realitzi. També se li exigeix prioritzar la prevenció de la generació de residus per sobre de la reutilització, i aquesta per sobre del reciclatge, i aquest últim per sobre de l'eliminació. Finalment, s'han de donar prioritat als gestors ubicats geogràficament a prop. L'Agència de Residus de Catalunya té competència sobre els residus que es generen a Catalunya i els que es gestionen al seu àmbit territorial. Queden exclosos de la seva competència els residus radioactius, els residus resultants de la prospecció, l’extracció, el tractament i l’emmagatzematge de recursos minerals i de l’explotació de pedreres, els residus d’explotacions agrícoles i ramaderes que no siguin perillosos i s’utilitzin exclusivament en el marc de l’explotació agrària, els explosius desclassificats, les aigües residuals i els efluents gasosos emesos a l’atmosfera. D34 | E27: Consulteu la Llei 7/2022
E28: Consulteu informació en normativa catalana en matèria de residus
B29: Medi ambient - materials d'embalatge | C29: Totes | D29: Atès que la indústria manufacturera produeix productes físics, els materials d'embalatge utilitzats per al transport i la distribució d'aquests productes són un factor crucial amb un impacte potencialment significatiu. Per aquesta raó, la Unió Europea ha implementat una nova legislació que requereix la reducció de l'ús de plàstics d'un sol ús i en prohibeix certes aplicacions. A més, des de l'1 de gener, va entrar en vigor la Llei 7/2022, que estableix un nou impost sobre els envasos de plàstic no reutilitzables. Per tant, és important cercar materials d'embalatge que generin un menor impacte sobre el medi ambient, adaptats a l'aplicació i la ubicació geogràfica dels productes. La Sustainable Packaging Coalition ofereix diverses iniciatives destinades a ajudar les empreses a reduir l'impacte ambiental dels seus envasos. | E29: Consulteu informació sobre el Sustainable Packaging Coalition
E30: Consulteu informació sobre la Llei de plàstics d'un sol ús
E31: Consulteu informació sobre impostos sobre els envasos de plàstic no reutilitzables
B32: Medi ambient - Emissions de carboni | C32: Totes | D32: El transport de materials i productes contribueix al canvi climàtic a causa de les emissions de carboni que genera. Si bé és possible reduir la petjada de carboni en les activitats mateixes mitjançant l'ús d'energies renovables, el transport en si també té un impacte significatiu. Per aquesta raó, és important considerar formes de transport sostenible, com ara mitjans de transport respectuosos envers el medi ambient o la selecció de proveïdors locals, entre altres mesures. En el sector de la logística, hi ha iniciatives destinades a reduir les emissions d'aquest sector. Un exemple d'aquestes iniciatives és Lean and Green, que ajuda les empreses logístiques a reduir les seves emissions i compta amb un sistema de classificació basat en el seu acompliment. | E32: Consulteu informació sobre la iniciativa Lean and Green
E33: Consulteu informació sobre l'Oficina Catalana de Canvi Climàtic
B34: Medi ambient - compra sostenible | C34: Totes | D34: És important avaluar la sostenibilitat dels possibles proveïdors i donar prioritat a aquells que tenen el millor acompliment en aspectes ambientals, socials i de governança (ESG). Per garantir la compra sostenible, les empreses poden establir una política de compra sostenible per a tots els seus proveïdors, avaluar i prioritzar els proveïdors segons el seu acompliment en ASG i certificacions de sostenibilitat de productes, com l'EU Ecolabel, i col·laborar per assegurar una millora contínua, entre altres mesures. Actualment, la Unió Europea està desenvolupant legislació per exigir a les grans empreses que garanteixin la sostenibilitat en les seves compres, en forma del CSDDD (Corporate Sustainable Due Diligence Directive proposal). | E34: Vegeu la ISO 20400:2017 sobre compra sostenible
E35: Consulteu informació sobre l'EU Ecolabel
B36: Social - Estratègia Catalana de Seguretat i Salut Laboral | C36: Totes | D36: L’Estratègia catalana de seguretat i salut laboral 2021-2026 té com a objectiu millorar les condicions de treball a Catalunya, reduir la sinistralitat laboral i promoure la prevenció de riscos laborals. És fruit del treball conjunt entre la Generalitat, patronals i sindicats, amb indicadors per avaluar-ne el progrés i una perspectiva de gènere transversal. | E36: Consulta informació sobre l'Estratègia Catalana de Seguretat i Salut Laboral
B37: Bon govern - Pla de govern de la Generalitat de Catalunya | C37: Totes | D37: Aquest Pla contempla un eix dedicat a la "Transformació Democràtica", que inclou aspectes com el "Bon govern i govern obert". Aquest enfocament pot ser rellevant per al sector, ja que promou la transparència, l'ètica i la responsabilitat en les pràctiques de govern, que poden ser aplicades o servir d'exemple per a les empreses del sector​. | E37: Consulta informació sobre el Pla de govern de la Generalitat de Catalunya
B40: Temes específics per a la indústria de fusta i paper
B41: Tema | C41: Aplica a | D41: Descripció | E41: Font
B42: Diversos - etiqueta ecològica | C42: Paper gràfic, paper tissú i productes tissú, papereria, paper impresa i bosses de paper | D42: Per fomentar l'oferta de productes sostenibles dins la Unió Europea, hi ha l'Ecoetiqueta. Aquesta etiqueta assenyala als consumidors que el producte compleix uns criteris de sostenibilitat exigents de la Unió Europea. Aquests criteris inclouen temes com ara: compliment de normes laborals bàsiques, condicions laborals, sostenibilitat de materials, gestió sostenible de l'aigua, seguretat química i eficiència energètica. D'altra banda, a Catalunya hi ha un sistema voluntari d'etiquetatge ecològic per identificar productes i serveis respectuosos envers el medi ambient que s'anomena Distintiu de garantia de qualitat ambiental. Els productes o serveis que són reconeguts per aquest Distintiu superen determinats requeriments de qualitat ambiental més enllà dels establerts com a obligatoris per la normativa vigent. | E42: Consulteu l'Ecoetiqueta UE - paper
E43: Consulteu informació sobre el Distintiu de garantia de qualitat ambiental per al sector de la fusta i el paper
B44: FSC / PEFC / SFI | C44: Paper i fusta | D44: Atès que les matèries primeres d'aquests sectors poden tenir un impacte ambiental substancial, hi ha diverses certificacions que tracten d'establir normes de bona gestió ambiental en la cadena de valor. Les certificacions FSC, PEFC i SFI exigeixen una gestió sostenible dels boscos i el respecte als drets de les comunitats locals (indigenes), projecten els serveis ecosistèmics que brinden els boscos i mantenen alts valors de conservació. Addicionalment, tracten de promoure l'ús de paper reciclat en els productes de paper. | E44: Consulteu informació sobre la FSC
E45: Consulteu el lloc web de PEFC
E46: Consulteu informació sobre la SFI
B47: Medi ambient - gestió de residus - EN 643 | C47: Paper | D47: L'estàndard EN 643 defineix les diferents qualitats de paper per a reciclatge i estableix criteris sobre què poden contenir els diversos graus de qualitat. Això ajuda venedors i compradors de paper reciclat a determinar la qualitat del producte ofert. Un dels criteris clau és la tolerància zero per a productes no relacionats amb el paper i materials no utilitzables. A més, és important que el paper pugui ser destintat amb facilitat, cosa que garanteix la seva reciclabilitat. | E47: Consulteu informació de l'EN 643
B48: Medi ambient - subministrament de matèries primeres: regulació contra la desforestació | C48: Paper | D48: La Unió Europea està treballant en una regulació destinada a combatre la deforestació en les cadenes de subministrament de matèries primeres específiques. El paper és una de les matèries primeres seleccionades que haurà de complir aquesta nova regulació proposada. Això significa que els venedors de paper en el mercat europeu hauran de dur a terme una diligència deguda per assegurar-se que les matèries primeres utilitzades en la fabricació del paper no hagin contribuït a la deforestació després de 2019. Això implica rastrejar les matèries primeres al llarg de la cadena de subministrament per garantir que la fusta utilitzada en la producció no prové de zones desforestades a partir de 2019. | E48: Consulteu la regulació contra la deforestació - UE
B49: Diversos - millors tecnologies disponibles | C49: Totes | D49: En les indústries de paper i fusta, és de summa importància adoptar les millors tecnologies disponibles, en línia amb els documents BREF, per millorar l'acompliment de sostenibilitat. Aquestes tecnologies avançades optimitzen l'eficiència dels processos de producció, redueixen el consum de recursos naturals i minimitzen les emissions de substàncies nocives. En seguir les directrius dels documents BREF, les empreses poden alinear les seves pràctiques amb estàndards europeus reconeguts, i millorar així la seva responsabilitat ambiental. A més, aquestes pràctiques sostenibles reforcen la imatge de l'empresa en demostrar un compromís real envers la protecció del medi ambient i atrauen consumidors conscients de la sostenibilitat. | E49: Consulteu el document BREF sobre les millors tecnologies disponibles per a la producció de polpa, paper i taulers
E50: Consulteu el document BREF sobre les millors tecnologies disponibles per a la producció de panells de fusta
B51: Medi ambient - circularitat | C51: Totes | D51: En el cas de productes físics, els impactes principals solen estar relacionats amb els materials necessaris per a la producció i els residus generats després del seu ús. Les empreses de comerç poden millorar el seu acompliment en sostenibilitat seleccionant productes fets de materials respectuosos envers el medi ambient i dissenyats per facilitar el manteniment, la reparació i el reciclatge. La Unió Europea ha desenvolupat un pla d'acció per promoure l'economia circular i reduir la quantitat de residus abocats. Dins d'aquest enfocament, l'ecodisseny o el disseny per a la circularitat són de gran importància, ja que el disseny d'un producte influeix en gran mesura en la seva capacitat posterior per ser reciclat. Catalunya Circular és el hub d’innovació i punt de trobada d’empreses i institucions que aporten solucions i estratègies per consolidar l’economia circular a Catalunya. La certificació Cradle to Cradle s'atorga a productes que compleixen els principis de l'economia circular, i la Fundació Ellen MacArthur proporciona informació sobre l'economia circular i com implementar-la. | E51: Catalunya Circular: l'Observatori d'economia circular
E52: Consulteu més informació sobre l'economia circular (Fundació Ellen McArthur)
E53: Consulteu més informació sobre el certificat Cradle to Cradle
E54: Consulteu informació sobre el Sustainable Packaging Coalition
B55: Medi ambient - Distintiu de garantia de qualitat ambiental | C55: Totes | D55: El Distintiu de garantia de qualitat ambiental és una etiqueta oficial que atorga la Generalitat de Catalunya a productes i serveis que superen determinats requisits de qualitat ambiental més enllà dels establerts com a obligatoris per la normativa vigent. Està dissenyat per ajudar els consumidors a identificar productes i serveis que han estat produïts de manera responsable i sostenible. | E55: Consulteu informació sobre el Distintiu de garantia de qualitat ambiental per a productes de cartró i cartronet reciclats
E56: Consulteu informació sobre el Distintiu de garantia de qualitat ambiental per a productes de fusta
B57: Diversos - Reglament EUTR (UE) | C57: Totes | D57: L’objectiu del Reglament EUTR és garantir que la fusta i els productes de la fusta que es comercialitzen dins la UE, ja siguin produïts a la Unió Europea mateixa o importats, provenen d’aprofitaments legals. | E57: Consulta informació sobre la informació el Reglament de Comercialització de fusta i productes derivats

Sheet Tractament de Residus i Aigua
D1: Indústria de tractament de residus i aigua | E1: Aquesta indústria és una agrupació de les activitats CNAE 36 fins a 39. Totes aquestes activitats estan vinculades al tractament de residus i/o aigües. Aquests sectors tenen impactes ambientals inherents, els quals són importants de monitorar. Addicionalment, les empreses sovint treballen amb substàncies perilloses amb potencials riscos per a la salut, per la qual cosa la seguretat i salut són temes clau també.
D3: Gestió sostenible de l'aigua | E3: Emissions de GEH | F3: Gestió de residus i materials perillosos | G3: Qualitat de l'Aire | H3: Seguretat química | I3: Eficiència energètica i energies renovables
B4: Descripció | C4: Medi ambient | D4: =HLOOKUP(D3,AUTO!$B$1:$AJ$2,2,FALSE) -> La gestió sostenible de l'aigua tracta d'assegurar que el consum i ús d'aquesta aigua per part de l'empresa estiguin alineats amb la capacitat de recuperar-se de l'ecosistema i no generin impactes negatius. Les necessitats de consumir aigua estan lligades al sector i a la ubicació de la planta. És important destacar que les empreses amb operacions en zones amb estrès hídric caldrà que avaluïn com fer una gestió sostenible dels recursos hídrics. Això inclou reduir el consum d'aigua, millorar la captura i reutilització de les aigües grises i millorar el tractament d'aigües residuals, entre d'altres. | E4: =HLOOKUP(E3,AUTO!$B$1:$AJ$2,2,FALSE) -> Les emissions de gasos amb efecte d'hivernacle i les energies renovables són categories estretament vinculades amb el canvi climàtic. Les empreses amb una major petjada de carboni contribueixen en major mesura al canvi climàtic. Reduir els impactes relacionats amb aquest tema requereix una reducció de la petjada de carboni de l'empresa. Això requereix una transició envers fonts d'energia renovables i la implementació d'estratègies per assolir emissions netes zero. | F4: =HLOOKUP(F3,AUTO!$B$1:$AJ$2,2,FALSE) -> La gestió de residus perillosos i no perillosos és un àmbit en constant evolució normativa. L'adequada gestió de residus i materials perillosos és clau per reduir la contaminació causada per l'empresa o els productes que posa al mercat. Optimitzar el disseny i la producció i treballar paral·lelament a millorar la gestió de residus és clau per transicionar envers una economia circular que redueixi la necessitat d'explotació de nous recursos naturals. Per tant, les empreses que gestionen els seus residus i eviten la seva generació són més sostenibles i estan més alineades amb els principis de l'economia circular. | G4: =HLOOKUP(G3,AUTO!$B$1:$AJ$2,2,FALSE) -> Les emissions de contaminants com el diòxid de sofre (SOx), el diòxid de nitrogen (NOx) i els Compostos Orgànics Volàtils (VOC), entre d'altres, poden tenir un impacte significatiu sobre la qualitat de l'aire. Una mala qualitat de l'aire pot tenir efectes negatius tant sobre el medi ambient com sobre la salut de les comunitats afectades. Per tant, les empreses que duen a terme operacions que produeixen emissions a l'aire han d'avaluar el seu impacte sobre la qualitat de l'aire mitjançant controls regulars duts a terme per l'autoritat ambiental competent. Les empreses podrien considerar la instal·lació de filtres i altres mesures destinades a reduir les emissions de contaminants atmosfèrics. | H4: =HLOOKUP(H3,AUTO!$B$1:$AJ$2,2,FALSE) -> Garantir la seguretat química és de gran importància per preservar els ecosistemes i protegir les comunitats properes a instal·lacions que empren substàncies químiques perilloses. Les empreses que comercialitzen productes que contenen substàncies químiques perilloses susceptibles d'entrar en contacte amb l'entorn natural o els usuaris d'aquests productes és essencial que prenguin totes les mesures necessàries per prevenir aquesta situació. Millorar la seguretat química pot implicar la recerca d'alternatives de materials per a l'ús en els seus productes, dissenyar productes de manera segura per prevenir fuites de substàncies i elaborar un pla de gestió de residus al final del cicle de vida del producte. | I4: =HLOOKUP(I3,AUTO!$B$1:$AJ$2,2,FALSE) -> L'eficiència energètica i les energies renovables se centren a disminuir el consum energètic respecte de la producció. Les empreses amb una alta eficiència energètica són més sostenibles ambientalment i econòmicament, ja que requereixen menys recursos (combustibles, electricitat, matèries primeres, etc.) per generar el mateix volum d'ingressos que una de menys eficient.
B5: Indicadors | D5: - Petjada hídrica total + Cadena de subministrament + Operacions directes + Distribució - Consum total d'aigua - Consum d'aigua per volum de negocis (€) - Consum d'aigua per producte (nombre o pes) - Consum d'aigua en àrees amb estrès hídric - Descàrrega total d'aigua - Descàrrega total d'aigua en àrees amb estrès hídric - % de reutilització de l'aigua - Volum total d'aigua rebut per a tractament | E5: - Petjada de carboni de l'empresa (abast 1, 2 i 3), incloent: + emissions relacionades amb combustibles fòssils + emissions relacionades amb electricitat adquirida + emissions de gasos refrigerants + Altres emissions vinculats amb els materials usats, viatges per a negocis, etc. - Capacitat per generar energia renovable - Energia generada amb operacions (biogàs, incineració) - Energia venuda - Emissions biogèniques procedents de compostatge | F5: - Residus totals rebuts + Residus perillosos rebuts + Residus no perillosos rebuts - Residus utilitzats com a matèria primera (per fer productes) - Residus totals sortints + Per a eliminació + Per a reutilització, recuperació, reciclatge - Productes sortints (obtinguts de residus) - % de residus destinats a eliminació | G5: - Emissions de SOx, NOx i Compostos Orgànics Volàtils (VOC) - Qualitat de l'aire interior - Emissions de NOx dels vehicles de transport a les ciutats | H5: - % del personal que treballa amb químics que tenen la formació adequada - Ús total (pes o volum) de químics identificats en els processos de producció - Reducció en l'ús de químics identificats en els processos de producció - % de recuperació dels químics utilitzats en processos - Emissions de substàncies danyoses a l'aigua, l'aire o el sòl | I5: - Consum energètic per kg de residu tractat o litre d'aigua tractada - Consum energètic per € de volum de negoci - Reducció d'emissions de CO2 - Taxa de conversió d'energia (eficiència per procés) - Hores d'operació dels equips - Consum energètic per tipus de font - Ràtio d'energia recuperada - Percentatge de millora en eficiència energètica
C6: Social | D6: Seguretat i qualitat del producte | E6: Salut i seguretat laboral | F6: Relacions amb les comunitats afectades
B7: Descripció | D7: =HLOOKUP(D6,AUTO!$B$1:$AJ$2,2,FALSE) -> La seguretat i qualitat són aspectes importants del producte, no només des d'una perspectiva econòmica, sinó també des d'una perspectiva de sostenibilitat. Falles de seguretat i/o qualitat del producte poden afectar negativament la salut o la seguretat dels usuaris, la qual cosa pot produir una varietat de riscos tant per a la reputació de l'empresa com legals. Algunes de les mesures que les empreses poden prendre per gestionar aquests riscos són dur a terme proves de productes i gestionar el contingut, els ingredients i els químics utilitzats en el producte. | E7: =HLOOKUP(E6,AUTO!$B$1:$AJ$2,2,FALSE) -> La salut i seguretat laboral hauria de ser una prioritat fonamental en qualsevol empresa. Totes les empreses han d'assegurar-se de proporcionar un entorn de treball segur i saludable per als seus empleats. Això és especialment crucial en aquelles empreses que duen a terme operacions perilloses o tenen el potencial d'afectar adversament la salut dels seus treballadors. Una de les mesures clau per assegurar la salut i seguretat dels empleats és designar un/a responsable de salut i seguretat la funció principal del qual consisteix a avaluar els riscos per als empleats i implementar mesures de mitigació corresponents. | F7: =HLOOKUP(F6,AUTO!$B$1:$AJ$2,2,FALSE) -> Les organitzacions tenen un impacte sobre les comunitats on operen, tant a través d'impactes físics com a través de la interacció amb els membres d'aquestes comunitats que treballen a l'empresa. Per tant, és fonamental establir relacions sòlides i respectuoses envers les comunitats afectades a través d'un diàleg que permeti comprendre i abordar els impactes negatius generats per les operacions. Algunes eines que es poden utilitzar per mantenir relacions efectives amb les comunitats inclouen la realització de reunions periòdiques amb representants de la comunitat, la incorporació de membres de la societat a l'empresa i el manteniment d'una comunicació constant amb organitzacions locals.
B8: Indicadors | D8: - Taxa de queixes sobre els productes - Taxa d'enretirades dels productes - Taxa de no-conformitats amb requisits de qualitat i/o seguretat - Taxa de contaminació per objectes estranys - Seguretat microbiològica - Gestió d'al·lèrgens - Vida útil del producte | E8: - Taxa d'accidentalitat (per x empleats o per x hores treballades) - Índex de freqüència d'accidents (i canvis respecte d'altres anys) - Índex de gravetat d'accidents - Taxa de malalties laborals - Participació en formacions de seguretat - Taxa de compliment de procediments de seguretat - Nombre d'inspeccions de seguretat realitzades - Freqüència d'avaluació dels riscos laborals | F8: - Freqüència de sessions d'interacció amb els grups d'interès de l'empresa - Inversions en les comunitats afectades per part de l'empresa (infraestructura, escoles, centres de salut, etc.) - Nombre d'empleats de comunitats locals (especialment en comunitats marginalitzades)
C9: Governança | D9: Bon govern | E9: Gestió de riscos sistèmics
B10: Descripció | D10: =HLOOKUP(D9,AUTO!$B$1:$AJ$2,2,FALSE) -> El bon govern és un tema ampli, enfocat en la gestió responsable i ètica de l'organització en general. L'acompliment de bon govern està vinculat als codis ètics de l'empresa, l'estructura de la propietat i el control de l'empresa, la junta directiva (i la seva remuneració), una comptabilitat transparent, la política fiscal i la transparència. | E10: =HLOOKUP(E9,AUTO!$B$1:$AJ$2,2,FALSE) -> La gestió de riscos sistèmics s'enfoca a la contribució d'una empresa pel que fa als riscos sistèmics que amenacen els sistemes econòmics, socials, ambientals i tecnològics dels quals la societat depèn. Exemples d'aquests riscos inclouen el consum excessiu d'aigua per part d'una empresa que opera en una zona que ja pateix estrès hídric. Per millorar la seva gestió de la sostenibilitat, l'organització pot avaluar els seus impactes i aplicar plans i mesures de mitigació, entre altres accions.
B11: Indicadors | D11: =HLOOKUP(D9,AUTO!$AE$1:$AE$3,3,FALSE) -> - Composició de la junta directiva - % de membres independents dins la junta directiva - Existència de canals de denúncies i protecció de les parts interessades involucrades - % d'alts càrrecs investigats o condemnats - Compliment de codis (ètic, conducta, etc.) i normatives - % dels empleats (incloent-hi junta directiva) amb remuneració basada en la consecució d'objectius de sostenibilitat. - Auditories i certificacions independents | E11: - % de materials recuperats - Índex de qualitat de l'aigua abocada - Capacitat de tractament - % de reducció de residus destinats a l'eliminació - % de reducció de residus destinats a abocament - Gestió adequada de residus perillosos - Plans de contingència - Freqüència d'avaluació de vulnerabilitat i riscos - Resiliència al canvi climàtic - Control d'olors i emissions
B13: Mesures de gestió generals
B14: Tema | C14: Aplica a | D14: Descripció | E14: Fonts
B15: Bon govern - conducta de negocis | C15: Totes | D15: Comptar amb un codi de conducta que estableixi normes per a tots els empleats. Aquest document s'haurà d'alinear amb les normatives vigents per al sector, incloent especialment temes ambientals (contaminació de l'aire, aigua, sòl, impactes sobre la biodiversitat, emissions GEH, etc.), drets humans, condicions laborals, seguretat, anticorrupció i suborn, promoció de la igualtat (de gènere) i la inclusió de tothom. | E15: Consulteu més informació sobre el codi de conducta
B16: Bon govern - control de qualitat | C16: Totes | D16: L'empresa ha d'establir un sistema de gestió i control de qualitat per a tots els serveis i productes oferts a fi d'assegurar la qualitat del producte i la seguretat per als clients. És una bona pràctica certificar aquest sistema de gestió amb una ISO9001. | E16: Vegeu informació sobre la ISO 9001
B17: Impacte ambiental - sistema de gestió ambiental | C17: Totes | D17: L'empresa ha d'establir un sistema de gestió mediambiental que permeti identificar i avaluar els impactes potencials i reals i els riscos i les oportunitats relacionats amb la sostenibilitat de l'empresa. Els marcs per desenvolupar un sistema de gestió mediambiental són l'EMAS de la Unió Europea i la ISO14001. | E17: Consulteu informació sobre EMAS
E18: Vegeu informació sobre la ISO 14001.
B19: General - estat d'informe no financer | C19: Totes | D19: Els requisits de divulgació d'informació no financera, especialment pel que fa a la sostenibilitat, estan guanyant rellevància tant per a inversors com per a organismes públics. Aquesta tendència es troba estretament vinculada amb les regulacions de la Unió Europea en el marc del Pla de finances sostenibles i el Pacte verd. Tant la Directiva d'informació corporativa sostenible (CSRD) com la Llei 11/2018 harmonitzen els requisits de divulgació per a les grans empreses. Aquestes i altres iniciatives estan generant un efecte dominó sobre les cadenes de valor i el sistema financer, la qual cosa està portant a una major demanda d'informació per part d'empreses de totes les mides. Per tant, la divulgació d'informació sobre sostenibilitat reforça la posició d'una empresa en el mercat. Per a les petites i mitjanes empreses (PIME) que volen començar a divulgar informació no financera, el marc de referència GRI pot servir com a base. | E19: Consulteu més informació sobre la CSRD
E20: Consulteu la Llei 11/2018
E21: Consulteu més informació sobre el marc GRI
B22: Medi ambient - emissions de GEH | C22: Totes | D22: Calcular la petjada de carboni i adoptar fonts d'energia renovable beneficia les empreses de diverses maneres. Avaluar la petjada de carboni demostra un compromís ambiental sòlid, enforteix la reputació i atrau clients sensibles a la sostenibilitat. La instal·lació de fonts d'energia renovable, com ara panells solars, no només redueix els costos a llarg termini, sinó que també disminueix la dependència envers els combustibles fòssils, cosa que al seu torn ajuda a mitigar l'impacte ambiental. A més d'aquests beneficis, complir objectius d'energia sostenible pot generar incentius fiscals i subvencions que milloren la rendibilitat de l'empresa. Aquestes accions no només aporten beneficis econòmics i mediambientals, sinó que també reforcen la responsabilitat social de l'empresa i la posicionen com a líder en pràctiques empresarials sostenibles. | E22: Consulteu informació sobre el Protocol de GEH
E23: Consulteu informació sobre l'Oficina Catalana de Canvi Climàtic
B25: Medi Ambient - Eficiència energètica | C25: Totes | D25: L'eficiència energètica exerceix un paper fonamental en la reducció de les emissions de gasos amb efecte d'hivernacle de qualsevol empresa. Millorar l'eficiència energètica permet a una empresa generar valor amb un menor ús de recursos escassos. El document BREF de la Unió Europea proporciona orientació específica per assolir un ús eficient dels recursos i l'energia en diversos sectors i promou l'adopció de pràctiques sostenibles i alineades amb els objectius de la UE. Això no només beneficia la sostenibilitat econòmica de l'empresa, sinó que també contribueix a combatre el canvi climàtic. | E25: Consulteu el Document de referència sobre les millors tecnologies disponibles en termes d'eficiència energètica
B26: Social - Pla d'igualtat de gènere | C26: Empreses amb més de 50 treballadors | D26: L'empresa ha d'implementar un pla d'igualtat de gènere en compliment del Reial decret 901/2020. Aquest requisit implica que les empreses han d'adoptar, amb negociació prèvia, mesures destinades a prevenir qualsevol forma de discriminació laboral entre dones i homes i a fomentar condicions de treball que evitin l'assetjament sexual i l'assetjament per raó de gènere. A més, han d'establir procediments específics per a la prevenció d'aquests comportaments i per gestionar les denúncies o reclamacions presentades per qui n'hagi estat víctima. | E26: Consulteu el Reial decret 901/2020
B27: Medi ambient - compra sostenible | C27: Totes | D27: És important avaluar la sostenibilitat dels possibles proveïdors i donar prioritat a aquells que tenen el millor acompliment en aspectes ambientals, socials i de governança (ESG). Per garantir la compra sostenible, les empreses poden establir una política de compra sostenible per a tots els seus proveïdors, avaluar i prioritzar els proveïdors segons el seu acompliment en ASG i certificacions de sostenibilitat de productes, com l'EU Ecolabel, i col·laborar per assegurar una millora contínua, entre altres mesures. Actualment, la Unió Europea està desenvolupant legislació per exigir a les grans empreses que garanteixin la sostenibilitat en les seves compres, en forma del CSDDD (Corporate Sustainable Due Diligence Directive proposal). | E27: Vegeu la ISO 20400:2017 sobre compra sostenible
E28: Consulteu informació sobre l'EU Ecolabel
B29: Social - Estratègia Catalana de Seguretat i Salut Laboral | C29: Totes | D29: L’Estratègia catalana de seguretat i salut laboral 2021-2026 té com a objectiu millorar les condicions de treball a Catalunya, reduir la sinistralitat laboral i promoure la prevenció de riscos laborals. És fruit del treball conjunt entre la Generalitat, patronals i sindicats, amb indicadors per avaluar-ne el progrés i una perspectiva de gènere transversal. | E29: Consulta informació sobre l'Estratègia Catalana de Seguretat i Salut Laboral
B30: Bon govern - Pla de govern de la Generalitat de Catalunya | C30: Totes | D30: Aquest Pla contempla un eix dedicat a la "Transformació Democràtica", que inclou aspectes com el "Bon govern i govern obert". Aquest enfocament pot ser rellevant per al sector, ja que promou la transparència, l'ètica i la responsabilitat en les pràctiques de govern, que poden ser aplicades o servir d'exemple per a les empreses del sector​. | E30: Consulta informació sobre el Pla de govern de la Generalitat de Catalunya
B33: Temes específics per a la indústria de gestió de residus i tractament d'aigua
B34: Tema | C34: Aplica a | D34: Descripció | E34: Fonts
B35: Diversos - UE taxonomia | C35: Captació, depuració, tractament i distribució d'aigua | D35: La taxonomia defineix quines activitats econòmiques es consideren sostenibles dins la Unió Europea. Complir els criteris pot ajudar a millorar l'accés a finançament per a l'empresa o per a projectes específics que hi estiguin alineats. En el cas de sistemes relacionats amb la captació, depuració i distribució d'aigües, els criteris aborden els temes següents: eficiència energètica, gestió sostenible de l'aigua, adaptació al canvi climàtic, impacte sobre ecosistemes i biodiversitat, entre d'altres. | E35: Consulteu la taxonomia UE
E36: Consulteu els criteris tècnics de selecció per considerar quan una activitat econòmica contribueix a la mitigació o a l'adaptació al canvi climàtic
B37: Diversos - UE taxonomia | C37: Recollida i transport i valorització de residus | D37: La taxonomia defineix quines activitats econòmiques es consideren sostenibles dins la Unió Europea. Complir els criteris pot ajudar a millorar l'accés a finançament per a l'empresa o per a projectes específics que hi estiguin alineats a mitjà termini. En el cas de sistemes relacionats amb la captació, depuració i distribució d'aigües, els criteris aborden els temes següents: percentatge de residus valoritzats, separació dels residus, mitigació del canvi climàtic, adaptació al canvi climàtic i prevenció de la contaminació o altres impactes ambientals. Pel que fa a la gestió de residus, s'enfoca principalmente en aspectes qualitatius de la manera de gestionar-los (segregació en origen, recuperació material, etc.). | E37: Consulteu la taxonomia UE
E38: Consulteu els criteris tècnics de selecció per considerar quan una activitat econòmica contribueix a la mitigació o a l'adaptació al canvi climàtic
B39: Medi ambient - gestió de residus: EC 2150/2002 | C39: Tractament de residus | D39: Dins de la Unió Europea, hi ha un sistema uniforme per registrar els residus, cosa que permet rastrejar-los per tipus, des de l'empresa que els genera fins als gestors de residus. Aquest sistema es va establir en la legislació EC 2150/2002 i és fonamental per portar un registre coherent de la quantitat de residus tractats pels gestors de residus. | E39: Consulteu l'EC 2150/2002
B40: Diversos - Llei 7/2022 | C40: Tractament de residus | D40: La Llei 07/2022, de 8 d'abril, de residus i sòls contaminats per una economia circular, amplia la responsabilitat del productor de residus, la qual cosa podria implicar requisits més rigorosos per a la seva gestió. A més, estableix l'obligació de realitzar separacions de residus en els casos en què el productor no ho faci; en el seu lloc, el productor haurà de garantir que un gestor de residus realitzi aquesta separació. També cal que se segueixi la jerarquia de residus, la qual cosa pot influir en les activitats dels gestors de residus. Finalment, la Llei introdueix la necessitat de buscar gestors de residus geogràficament propers, la qual cosa pot presentar tant oportunitats com desafiaments. Això podria propiciar la captació de clients més propers, tot i que també podria generar una major competència per aquests clients. | E40: Consulteu la Llei 7/2022
B41: Medi Ambient - Circularitat | C41: Totes | D41: La circularitat és de summa importància per als gestors de residus, ja que representa un enfocament transformador en la gestió de deixalles. Adoptar enfocaments circulars implica el pas d'un model lineal de consum i eliminació a un en el qual els materials es reutilitzen, reciclen i reincorporen en la cadena productiva. Això ofereix oportunitats significatives. Els gestors poden generar noves fonts d'ingressos a través de la venda de materials reciclats i l'oferta de serveis de gestió sostenible. A més, es redueixen els costos d'eliminació i es minimitza la pressió sobre els recursos naturals. La circularitat també millora la reputació en mostrar un compromís genuí amb la sostenibilitat, cosa que atrau clients i socis que valoren la responsabilitat ambiental i contribueix a la creació d'un futur més resilient i ecoeficient. Catalunya Circular és el hub d’innovació i punt de trobada d’empreses i institucions que aporten solucions i estratègies per consolidar l’economia circular a Catalunya. | E41: Consulta informació sobre Catalunya Circular, l'Observatori d'economia circular
E42: Consulteu el Pla d'acció per a l'economia circular (UE)
B43: Diversos - millors tecnologies disponibles | C43: Tractament de residus | D43: L'adopció de les millors tecnologies, seguint les directrius dels documents BREF de la Unió Europea, és de gran benefici per a la sostenibilitat dels gestors de residus. Aquestes tecnologies avançades optimitzen l'eficiència de la gestió de residus, la qual cosa comporta una reducció dels impactes ambientals i el compliment de les normatives. Això al seu torn promou la seguretat de la salut pública i de l'entorn. A més, aquestes pràctiques avançades fomenten l'economia circular en reciclar i reutilitzar de manera més eficient. La implementació d'aquestes tecnologies pot generar estalvis a llarg termini en optimitzar processos i reduir costos. En conjunt, l'adopció de les millors tecnologies segons els documents BREF reforça l'acompliment sostenible dels gestors de residus i millora tant la protecció del medi ambient com la salut econòmica. | E43: Consulteu el document sobre les millors tecnologies disponibles per a la incineració de residus
E44: Consulteu el document sobre les millors tecnologies disponibles per al tractament de residus
B45: Medi ambient - emissions de carboni | C45: Totes | D45: Les emissions de carboni contribueixen al canvi climàtic i tenen un impacte ambiental negatiu significatiu. En reduir aquestes emissions, l'empresa contribueix directament a la mitigació de l'escalfament global. A més, la millora de l'eficiència en el transport pot generar estalvis econòmics en optimitzar les rutes i reduir el consum de combustible. Des d'una perspectiva reputacional, la gestió responsable del transport reflecteix el compromís ambiental de l'empresa i pot atreure clients i socis que valoren la sostenibilitat. És especialment rellevant perquè els clients cerquen reduir les seves petjades de carboni a través de l'abast 3, que inclou la gestió de residus. Per tant, oferir serveis de transport amb baixes emissions pot proporcionar un avantatge competitiu. | E45: Consulteu la informació sobre la iniciativa Lean and Green
B46: Diversos- Gestió de residus municipals | C46: Totes | D46: El model de gestió vigent i les bases de la planificació es fonamenten, entre d’altres, en els principis de proximitat, de suficiència i de responsabilitat del productor, i també en la jerarquia establerta per a les diferents formes de gestió, que dóna prioritat a les actuacions de prevenció. | E46: Consulta informació sobre el Programa de gestió de residus municipals
B47: Diversos - Normativa en matèria de residus | C47: Totes | D47: L'Agència de Residus de Catalunya té competència sobre els residus que es generen a Catalunya i els que es gestionen al seu àmbit territorial. Queden exclosos de la seva competència els residus radioactius, els residus resultants de la prospecció, l’extracció, el tractament i l’emmagatzematge de recursos minerals i de l’explotació de pedreres, els residus d’explotacions agrícoles i ramaderes que no siguin perillosos i s’utilitzin exclusivament en el marc de l’explotació agrària, els explosius desclassificats, les aigües residuals i els efluents gasosos emesos a l’atmosfera. | E47: Consulta informació sobre la normativa en matèria de residus

Sheet Construcció
D1: Indústria de la construcció | E1: Aquest grup d'activitats és la combinació de CNAE 41 i 43, relacionades amb la construcció d'edificis i la construcció especialitzada, respectivament.
D3: Oportunitats de construcció sostenible | E3: Biodiversitat i ecosistemes | F3: Emissions de GEH | G3: Eficiència energètica i energies renovables | H3: Gestió sostenible de l'aigua | I3: Disseny del producte i gestió del cicle de vida | J3: Impactes físics del canvi climàtic | K3: Subministrament de matèries primeres / productes venuts
B4: Descripció | C4: Medi ambient | D4: =HLOOKUP(D3,AUTO!$B$1:$AJ$2,2,FALSE) -> Les oportunitats de tecnologies/aplicacions sostenibles són rellevants per als sectors on hi ha tecnologies verdes o aplicacions sostenibles que es podrien implementar per afavorir la sostenibilitat de l'empresa. Per exemple, la instal·lació de capacitat de renovables en el sector de l'energia o les aplicacions de tecnologies verdes en la construcció de nous edificis per al sector de l'edificació són oportunitats importants per diferenciar-se de la competència en termes de sostenibilitat. | E4: =HLOOKUP(E3,AUTO!$B$1:$AJ$2,2,FALSE) -> Aquesta categoria se centra en els impactes de les operacions o els actius d'una empresa sobre ecosistemes i la seva biodiversitat. Les activitats amb potencials impactes significatius són aquelles vinculades amb canvis en l'ús del sòl per a exploració/explotació de recursos naturals, construcció, agricultura extensiva, etc. Els impactes poden produir pèrdua de biodiversitat, destrucció d'hàbitats, deforestació i pèrdua de serveis ecosistèmics bàsics. Les empreses haurien d'avaluar les seves dependències i impactes sobre el capital natural (natura), mitigar els riscos associats i fomentar un impacte positiu en totes les fases de la cadena de valor de l'empresa. | F4: =HLOOKUP(F3,AUTO!$B$1:$AJ$2,2,FALSE) -> Les emissions de gasos amb efecte d'hivernacle i les energies renovables són categories estretament vinculades amb el canvi climàtic. Les empreses amb una major petjada de carboni contribueixen en major mesura al canvi climàtic. Reduir els impactes relacionats amb aquest tema requereix una reducció de la petjada de carboni de l'empresa. Això requereix una transició envers fonts d'energia renovables i la implementació d'estratègies per assolir emissions netes zero. | G4: =HLOOKUP(G3,AUTO!$B$1:$AJ$2,2,FALSE) -> L'eficiència energètica i les energies renovables se centren a disminuir el consum energètic respecte de la producció. Les empreses amb una alta eficiència energètica són més sostenibles ambientalment i econòmicament, ja que requereixen menys recursos (combustibles, electricitat, matèries primeres, etc.) per generar el mateix volum d'ingressos que una de menys eficient. | H4: =HLOOKUP(H3,AUTO!$B$1:$AJ$2,2,FALSE) -> La gestió sostenible de l'aigua tracta d'assegurar que el consum i ús d'aquesta aigua per part de l'empresa estiguin alineats amb la capacitat de recuperar-se de l'ecosistema i no generin impactes negatius. Les necessitats de consumir aigua estan lligades al sector i a la ubicació de la planta. És important destacar que les empreses amb operacions en zones amb estrès hídric caldrà que avaluïn com fer una gestió sostenible dels recursos hídrics. Això inclou reduir el consum d'aigua, millorar la captura i reutilització de les aigües grises i millorar el tractament d'aigües residuals, entre d'altres. | I4: =HLOOKUP(I3,AUTO!$B$1:$AJ$2,2,FALSE) -> El disseny dels productes i els seus cicles de vida són molt importants per gestionar l'impacte mediambiental de l'empresa. L'ecodisseny pot facilitar la reparació i el manteniment del producte i millorar-ne la tria dels materials més adequats i la reuitilització. Un correcte ecodisseny assegura una reducció dels impactes en tot el cicle de vida del producte. Les empreses que tenen en compte els impactes durant tot el cicle de vida permeten reduir l'impacte total del producte o servei en l'ús de materials, disseny industrial, producció i gestió de residus. D'aquesta manera, les empreses s'adapten als esquemes de responsabilitat ampliada del productor o futures normatives enfocades a la circularitat de l'economia. | J4: =HLOOKUP(J3,AUTO!$B$1:$AJ$2,2,FALSE) -> Els impactes físics del canvi climàtic són aquells que experimenta, experimentarà o ja ha experimentat l'empresa vinculats a modificacions en variables climàtiques. Per exemple, la manca d'aigua a causa d'una sequera prolongada, danys provocats per inundacions causades per una tempesta especialment forta, pedregades o els costos en què l'empresa ha d'incórrer per adaptar-se a un clima canviant. | K4: =HLOOKUP(K3,AUTO!$B$1:$AJ$2,2,FALSE) -> El subministrament de matèries primeres és un tema crucial per a la sostenibilitat d'aquells sectors molt intensius en materials. Aquí les empreses haurien d'avaluar oportunitats per a una adquisició de matèries de manera sostenible amb proveïdors confiables i certificats i estratègies de recuperació de material que es pugui recuperar com a matèria primera. Aquest tema pot ser important tant per a empreses que adquireixen matèries primeres com per a empreses que adquireixen prefabricats o productes. Un exemple és la cadena de subministrament d'empreses alimentàries, on és obligatori poder demostrar que el producte utilitzat no prové de zones amb alta deforestació.
B5: Indicadors | D5: - Instal·lacions sanitàries de baix cabal - Captació i utilització d'aigua pluvial - Taxa de recuperació d'aigües grises - Certificació d'eficiència energètica - Capacitat renovable autosuficient - Disseny bioclimàtic i ventilació natural - Taxa de separació i reciclatge dels residus - Ús de materials reciclats, reciclables i biomaterials - Ús de materials amb certificats de sostenibilitat - Ús de sensors i sistemes d'automatització | E5: - Conversió d'ecosistemes - Pròximitat a ecosistemes d'alt valor de biodiversitat - Pròximitat a zones naturals protegides - Súperfície afectada - Presència d'espècies vulnerables | F5: - Petjada de carboni de l'empresa (abast 1, 2 i 3), incloent: + emissions relacionades amb combustibles fòssils + emissions relacionades amb electricitat adquirida + emissions de gasos refrigerants + Altres emissions vinculades amb els materials usats, viatges per a negocis, etc. - Instal·lació de capacitat renovable en la nova construcció | G5: - Certificació d'eficiència energètica - Consum d'energia primària (per m2) - Aïllament tèrmic - Eficiència del sistema de climatització - Ús d'energia renovable (i % del total) - Ús de sensors i sistemes d'automatització | H5: - Cabals de les aixetes i les instal·lacions sanitàries - Captació d'aigües pluvials - Taxa de reutilització de les aigües grises - Eficiència de sistemes de reg - Petjada hídrica de materials de construcció - Incorporació de tecnologies de reciclatge d'aigua | I5: - Percentatge de materials reciclats o d'origen renovable utilitzats en la construcció - Percentatge de components reciclables o reutilitzables en el producte - Disseny del producte que faciliti el seu reciclatge o reutilització al final de la seva vida útil - Avaluació de l'impacte ambiental dels materials emprats al llarg del seu cicle de vida (anàlisi del cicle de vida) - Avaluació de l'impacte ambiental en la biodiversitat durant el cicle de vida dels materials i/o el projecte sencer | J5: - Avaluació dels riscos climàtics potencials relacionats amb el projecte - Percentatge de projectes que incorporen mesures d'adaptació al canvi climàtic en el seu disseny i construcció - Percentatge de projectes que integren infraestructures resistents a esdeveniments climàtics - Percentatge del pressupost dedicat a la inversió en infraestructures i projectes que millorin la resiliència davant el canvi climàtic | K5: - Percentatge de materials de fonts locals - Distància mitjana recorreguda pels materials - Tones de CO2 emeses per unitat de material produït - Percentatge de materials reciclats o reutilitzats - Percentatge de materials que compleixen estàndards de sostenibilitat (LEED, BREEAM, FSC, etc.) - Percentatge de materials amb certificacions de baix impacte ambiental - Puntuació de proveïdors segons criteris de sostenibilitat en la seva cadena de subministrament
D6: Salut i seguretat laboral | E6: Condicions laborals | F6: Seguretat i qualitat del producte
B7: Descripció | C7: Social | D7: =HLOOKUP(D6,AUTO!$B$1:$AJ$2,2,FALSE) -> La salut i seguretat laboral hauria de ser una prioritat fonamental en qualsevol empresa. Totes les empreses han d'assegurar-se de proporcionar un entorn de treball segur i saludable per als seus empleats. Això és especialment crucial en aquelles empreses que duen a terme operacions perilloses o tenen el potencial d'afectar adversament la salut dels seus treballadors. Una de les mesures clau per assegurar la salut i seguretat dels empleats és designar un/a responsable de salut i seguretat la funció principal del qual consisteix a avaluar els riscos per als empleats i implementar mesures de mitigació corresponents. | E7: =HLOOKUP(E6,AUTO!$B$1:$AJ$2,2,FALSE) -> Per tenir una bona consideració social i contribuir a una societat més justa, les empreses haurien d'oferir bones condicions laborals als seus empleats. Això no es limita al compliment dels drets humans; també inclou drets laborals, remuneració justa, horaris dignes, pagament d'hores extres, etc. Addicionalment, per anar més enllà dels compliments legals, les empreses poden oferir oportunitats de creixement, dret a desconnexió digital, posicions híbrides o en remot i altres mesures de conciliació per promoure l'equilibri entre la vida laboral i la personal. | F7: =HLOOKUP(F6,AUTO!$B$1:$AJ$2,2,FALSE) -> La seguretat i qualitat són aspectes importants del producte, no només des d'una perspectiva econòmica, sinó també des d'una perspectiva de sostenibilitat. Falles de seguretat i/o qualitat del producte poden afectar negativament la salut o la seguretat dels usuaris, la qual cosa pot produir una varietat de riscos tant per a la reputació de l'empresa com legals. Algunes de les mesures que les empreses poden prendre per gestionar aquests riscos són dur a terme proves de productes i gestionar el contingut, els ingredients i els químics utilitzats en el producte.
B8: Indicadors | D8: - Nombre d'accidents laborals per cada nombre determinat d'hores treballades - Taxa de dies perduts per accidents o malalties - Percentatge d'empleats capacitats en temes de salut i seguretat - Freqüència i resultats d'inspeccions de seguretat - Percentatge d'empleats que utilitzen EPI de manera adequada - Mesures implementades per prevenir caigudes des d'alçades - Accés a atenció mèdica - Mesures de manipulació segura de substàncies perilloses | E8: - Mitjana d'hores setmanals treballades per empleat - Mitjana de salaris dels empleats en comparació amb el salari mínim i els estàndards de la indústria - Oferta de beneficis addicionals, com ara assegurança de salut, assegurança de vida, etc. - Disponibilitat i accés a serveis mèdics per als empleats i les seves famílies - Percentatge d'empleats que reben formació i oportunitats de desenvolupament professional - Enquestes de satisfacció laboral per mesurar el clima laboral i la satisfacció dels empleats - Mesures implementades per facilitar l'equilibri entre la vida laboral i personal dels empleats - Taxa de rotació d'empleats a l'empresa | F8: - Percentatge de defectes trobats en la construcció que requereixen retreball o correccions - Avaluació del grau en què la construcció compleix les especificacions i plànols establerts - Existència i compliment de proves i certificacions de qualitat per als materials i components utilitzats - Enquestes de satisfacció del client i seguiment de la qualitat del producte després del lliurament - Existència i compliment de garanties ofertes al client per solucionar problemes postlliurament - Avaluació del rendiment i durabilitat dels materials utilitzats en la construcció
D9: Bon govern | E9: Resiliència del model de negoci | F9: Gestió de riscos d'incidents critics
B10: Descripció | C10: Governança | D10: =HLOOKUP(D9,AUTO!$B$1:$AJ$2,2,FALSE) -> El bon govern és un tema ampli, enfocat en la gestió responsable i ètica de l'organització en general. L'acompliment de bon govern està vinculat als codis ètics de l'empresa, l'estructura de la propietat i el control de l'empresa, la junta directiva (i la seva remuneració), una comptabilitat transparent, la política fiscal i la transparència. | E10: =HLOOKUP(E9,AUTO!$B$1:$AJ$2,2,FALSE) -> La resiliència del model de negoci fa referència a la capacitat de l'empresa d'adaptar-se als canvis relacionats amb les transicions ASG (mediambientals, socials i de bon govern). Això inclou la capacitat de mitigar riscos (com els reputacionals, legals i físics) i aprofitar les oportunitats que presenten els possibles nous mercats i productes i la diferenciació basada en la sostenibilitat. Les empreses més resilients compten amb sistemes de gestió de la sostenibilitat que identifiquen, avaluen i responen als riscos i les oportunitats potencials. | F10: =HLOOKUP(F9,AUTO!$B$1:$AJ$2,2,FALSE) -> La gestió de riscos d'incidents crítics és rellevant per a organitzacions que duen a terme activitats o operacions perilloses. En aquest context, les organitzacions que identifiquen, comprenen, prevenen i minimitzen els riscos d'incidents que podrien ocórrer aconseguiran un millor acompliment en termes de sostenibilitat en la seva governança corporativa. Les empreses poden millorar el seu rendiment mitjançant la promoció d'una cultura de seguretat, la implementació de tecnologies que ajudin en la gestió de riscos, la realització d'anàlisi de probabilitat i impacte dels riscos i l'aplicació de mesures per mitigar aquests riscos, entre altres accions.
B11: Indicadors | D11: =HLOOKUP(D9,AUTO!$AE$1:$AE$3,3,FALSE) -> - Composició de la junta directiva - % de membres independents dins la junta directiva - Existència de canals de denúncies i protecció de les parts interessades involucrades - % d'alts càrrecs investigats o condemnats - Compliment de codis (ètic, conducta, etc.) i normatives - % dels empleats (incloent-hi junta directiva) amb remuneració basada en la consecució d'objectius de sostenibilitat. - Auditories i certificacions independents | E11: - % de volum de negocis relacionat amb projectes amb certificat de sostenibilitat (LEED, BREEAM, etc.) - Fites relacionades amb la venda de serveis sostenibles - Tenir una estratègia per assegurar la sostenibilitat del negoci | F11: - Temps transcorregut des de la detecció d'un incident crític fins a la implementació de les accions de resposta i mitigació - Percentatge d'empleats capacitats i entrenats en els protocols de seguretat i procediments d'emergència - Avaluació del grau de compliment dels protocols d'evacuació i rescat en cas d'incidents crítics - Avaluació de l'efectivitat de la comunicació durant incidents crítics amb empleats, contractistes, clients i altres parts interessades - Avaluació del maneig de riscos en les activitats i els processos de proveïdors i subcontractistes - Avaluació del grau de compliment dels estàndards de seguretat específics de la indústria de la construcció
B13: Mesures de gestió generals
B14: Tema | C14: Aplica a | D14: Descripció | E14: Fonts
B15: Bon govern - conducta de negocis | C15: Totes | D15: Comptar amb un codi de conducta que estableixi normes per a tots els empleats. Aquest document s'haurà d'alinear amb les normatives vigents per al sector, incloent especialment temes ambientals (contaminació de l'aire, aigua, sòl, impactes sobre la biodiversitat, emissions GEH, etc.), drets humans, condicions laborals, seguretat, anticorrupció i suborn, promoció de la igualtat (de gènere) i la inclusió de tothom. | E15: Consulteu més informació sobre el codi de conducta
B16: Bon govern - control de qualitat | C16: Totes | D16: L'empresa ha d'establir un sistema de gestió i control de qualitat per a tots els serveis i productes oferts a fi d'assegurar la qualitat del producte i la seguretat per als clients. És una bona pràctica certificar aquest sistema de gestió amb una ISO9001. | E16: Vegeu informació sobre la ISO 9001
B17: Impactes ambientals - sistema de gestió ambiental | C17: Totes | D17: L'empresa ha d'establir un sistema de gestió mediambiental que permeti identificar i avaluar els impactes potencials i reals i els riscos i les oportunitats relacionats amb la sostenibilitat de l'empresa. Els marcs per desenvolupar un sistema de gestió mediambiental són l'EMAS de la Unió Europea i la ISO14001. | E17: Consulteu informació sobre EMAS
E18: Vegeu informació sobre la ISO 14001
B19: General - estat d'informe no financer | C19: Totes | D19: Els requisits de divulgació d'informació no financera, especialment pel que fa a la sostenibilitat, estan guanyant rellevància tant per a inversors com per a organismes públics. Aquesta tendència es troba estretament vinculada amb les regulacions de la Unió Europea en el marc del Pla de finances sostenibles i el Pacte verd. Tant la Directiva d'informació corporativa sostenible (CSRD) com la Llei 11/2018 harmonitzen els requisits de divulgació per a les grans empreses. Aquestes i altres iniciatives estan generant un efecte dominó sobre les cadenes de valor i el sistema financer, la qual cosa està portant a una major demanda d'informació per part d'empreses de totes les mides. Per tant, la divulgació d'informació sobre sostenibilitat reforça la posició d'una empresa en el mercat. Per a les petites i mitjanes empreses (PIME) que volen començar a divulgar informació no financera, el marc de referència GRI pot servir com a base. | E19: Consulteu més informació sobre la CSRD
E20: Consulteu la Llei 11/2018
E21: Consulteu més informació sobre el marc GRI
B22: Medi ambient - emissions de GEH | C22: Totes | D22: Calcular la petjada de carboni i adoptar fonts d'energia renovable beneficia les empreses de diverses maneres. Avaluar la petjada de carboni demostra un compromís ambiental sòlid, enforteix la reputació i atrau clients sensibles a la sostenibilitat. La instal·lació de fonts d'energia renovable, com ara panells solars, no només redueix els costos a llarg termini, sinó que també disminueix la dependència envers els combustibles fòssils, cosa que al seu torn ajuda a mitigar l'impacte ambiental. A més d'aquests beneficis, complir objectius d'energia sostenible pot generar incentius fiscals i subvencions que milloren la rendibilitat de l'empresa. Aquestes accions no només aporten beneficis econòmics i mediambientals, sinó que també reforcen la responsabilitat social de l'empresa i la posicionen com a líder en pràctiques empresarials sostenibles. | E22: Consulteu informació sobre el Protocol de GEH
E23: Consulteu informació sobre l'Oficina Catalana de Canvi Climàtic
B25: Medi ambient - eficiència energètica | C25: Totes | D25: L'eficiència energètica exerceix un paper fonamental en la reducció de les emissions de gasos amb efecte d'hivernacle de qualsevol empresa. Millorar l'eficiència energètica permet a una empresa generar valor amb un menor ús de recursos escassos. El document BREF de la Unió Europea proporciona orientació específica per assolir un ús eficient dels recursos i l'energia en diversos sectors i promou l'adopció de pràctiques sostenibles i alineades amb els objectius de la UE. Això no només beneficia la sostenibilitat econòmica de l'empresa, sinó que també contribueix a combatre el canvi climàtic. | E25: Consulteu el Document de referència sobre les millors tecnologies disponibles en termes d'eficiència energètica
B26: Protecció de dades - política de protecció de dades | C26: Totes | D26: L'empresa ha d'establir una política de protecció de dades, alineades amb la llei de protecció de dades de la UE. Tot el personal ha de rebre formació per gestionar dades del client de manera adequada i hi ha d'haver un protocol de contigència per a casos d'emergència. Adjunt a la columna de fonts trobareu un exemple d'una política de protecció de dades de l'Agència Catalana de Turisme. | E26: Consulteu un exemple d'una política de protecció de dades
B27: Bon govern - conducta de proveïdors | C27: Totes | D27: L'empresa ha d'establir un codi de conducta per als seus proveïdors i altres actors en la cadena de valor del negoci. Aquest codi ha de ser signat pels proveïdors i exigir-ne el compliment amb els estàndards de bon govern establerts en el document. Es recomana alinear aquest codi de conducta amb el codi de conducta intern, encara que en certs casos es pot permetre certa flexibilitat, sempre que continuï estant de conformitat amb les regulacions vigents relacionades amb la cadena de valor, com aquelles relacionades amb la no deforestació, els drets humans o les emissions de carboni, entre d'altres. A la columna 'Fonts' adjunta, trobareu un exemple d'un codi de conducta/ètic per a proveïdors del Pacte Mundial de Nacions Unides. | E27: Consulteu un exemple de codi de conducta/ètic de proveïdors
B28: Social - Pla d'igualtat de gènere | C28: Empreses amb més de 50 treballadors | D28: L'empresa ha d'implementar un pla d'igualtat de gènere en compliment del Reial decret 901/2020. Aquest requisit implica que les empreses han d'adoptar, amb negociació prèvia, mesures destinades a prevenir qualsevol forma de discriminació laboral entre dones i homes i a fomentar condicions de treball que evitin l'assetjament sexual i l'assetjament per raó de gènere. A més, han d'establir procediments específics per a la prevenció d'aquests comportaments i per gestionar les denúncies o reclamacions presentades per qui n'hagi estat víctima. | E28: Consulteu el Reial decret 901/2020
B29: Medi ambient - residus | C29: Totes | D29: A partir de l'1 de gener de 2023, va entrar en vigor la Llei 7/2022, de 8 d'abril, de residus i sòls contaminats per una economia circular, que amplia la responsabilitat del productor de residus fins que aquests residus hagin estat gestionats per un gestor final. Això té implicacions per a totes les empreses que generen residus, ja que s'han d'assegurar que els residus siguin tractats o eliminats de manera adequada. A més, la Llei estableix que el productor de residus ha de fer separacions mínimes o garantir que un gestor les realitzi. També se li exigeix prioritzar la prevenció de la generació de residus per sobre de la reutilització, i aquesta per sobre del reciclatge, i aquest últim per sobre de l'eliminació. Finalment, s'han de donar prioritat als gestors ubicats geogràficament a prop. L'Agència de Residus de Catalunya té competència sobre els residus que es generen a Catalunya i els que es gestionen al seu àmbit territorial. Queden exclosos de la seva competència els residus radioactius, els residus resultants de la prospecció, l’extracció, el tractament i l’emmagatzematge de recursos minerals i de l’explotació de pedreres, els residus d’explotacions agrícoles i ramaderes que no siguin perillosos i s’utilitzin exclusivament en el marc de l’explotació agrària, els explosius desclassificats, les aigües residuals i els efluents gasosos emesos a l’atmosfera. | E29: Consulteu la Llei 7/2022
E30: Consulteu informació sobre la normativa catalana en matèria de residus
B31: Medi ambient - compra sostenible | C31: Totes | D31: És essencial avaluar la sostenibilitat dels possibles proveïdors i donar prioritat a aquells que demostrin un sòlid acompliment en aspectes ambientals, socials i de govern corporatiu, coneguts com a ASG. Per garantir la compra sostenible, les empreses poden establir una política de compres sostenibles que s'apliqui a tots els seus proveïdors. Això implica avaluar i prioritzar els proveïdors segons el seu acompliment en àrees ASG i buscar certificacions de sostenibilitat de productes, com ara l'EU Ecolabel. A més, es pot fomentar la col·laboració amb els proveïdors per impulsar una millora contínua en matèria de sostenibilitat. És important destacar que la Unió Europea està treballant actualment en una legislació, coneguda com a CSDDD, que requerirà que les grans empreses assegurin la sostenibilitat en les seves compres. Això subratlla encara més la importància d'adoptar pràctiques de compra sostenible en el mercat actual. | E31: Consulteu la ISO 20400:2017 sobre compra sostenible
E32: Consulteu informació sobre l'EU Ecolabel
B33: Social - Estratègia Catalana de Seguretat i Salut Laboral | C33: Totes | D33: L’Estratègia catalana de seguretat i salut laboral 2021-2026 té com a objectiu millorar les condicions de treball a Catalunya, reduir la sinistralitat laboral i promoure la prevenció de riscos laborals. És fruit del treball conjunt entre la Generalitat, patronals i sindicats, amb indicadors per avaluar-ne el progrés i una perspectiva de gènere transversal. | E33: Consulta informació sobre l'Estratègia Catalana de Seguretat i Salut Laboral
B34: Bon govern - Pla de govern de la Generalitat de Catalunya | C34: Totes | D34: Aquest Pla contempla un eix dedicat a la "Transformació Democràtica", que inclou aspectes com el "Bon govern i govern obert". Aquest enfocament pot ser rellevant per al sector, ja que promou la transparència, l'ètica i la responsabilitat en les pràctiques de govern, que poden ser aplicades o servir d'exemple per a les empreses del sector​. | E34: Consulta informació sobre el Pla de govern de la Generalitat de Catalunya
B37: Temes específics per a la indústria de la construcció
B38: Tema | C38: Aplica a | D38: Descripció | E38: Fonts
B39: Taxonomia UE | C39: Noves construccions | D39: La taxonomia defineix quines activitats econòmiques es consideren sostenibles dins la Unió Europea. Complir els seus criteris, que abasten l'eficiència energètica, l'ús d'energies renovables, l'adaptació al canvi climàtic, la gestió sostenible dels recursos hídrics, la promoció de la circularitat i la protecció dels ecosistemes i la biodiversitat, brinda a les empreses un millor accés al finançament de fons europeus i altres inversors. | E39: Consulteu la taxonomia UE
E40: Consulteu els criteris tècnics de selecció per considerar quan una activitat econòmica contribueix a la mitigació o a l'adaptació al canvi climàtic
B41: Taxonomia UE | C41: Renovació d'edificis existents | D41: La taxonomia defineix quines activitats econòmiques es consideren sostenibles dins la Unió Europea. Complir els seus criteris, que abasten l'eficiència energètica, l'ús d'energies renovables, l'adaptació al canvi climàtic, la gestió sostenible dels recursos hídrics, la promoció de la circularitat i la protecció dels ecosistemes i la biodiversitat, brinda a les empreses un millor accés al finançament de fons europeus i altres inversors. | E41: Consulteu la taxonomia UE
E42: Consulteu els criteris tècnics de selecció per considerar quan una activitat econòmica contribueix a la mitigació o a l'adaptació al canvi climàtic
B43: Taxonomia UE | C43: Instal·lació, manteniment i reparació de tecnologies verdes | D43: La taxonomia defineix quines activitats econòmiques es consideren sostenibles dins la Unió Europea. Complir els seus criteris, que abasten l'eficiència energètica, l'ús d'energies renovables, l'adaptació al canvi climàtic, la gestió sostenible dels recursos hídrics, la promoció de la circularitat i la protecció dels ecosistemes i la biodiversitat, brinda a les empreses un millor accés al finançament de fons europeus i altres inversors. | E43: Consulteu la taxonomia UE
E44: Consulteu els criteris tècnics de selecció per considerar quan una activitat econòmica contribueix a la mitigació o a l'adaptació al canvi climàtic
B45: Certificacions BREEAM, LEED i GBCE | C45: Noves construccions | D45: Les certificacions de BREEAM i LEED són reconegudes internacionalment com a estàndard d'edificacions sostenibles. Aquests marcs contenen requisits ambientals relacionats amb eficiència energètica, emissions, gestió de l'aigua, gestió de materials i circularitat, entre d'altres. Addicionalment, contenen un component social, que exigeix la seguretat de l'edifici per a la salut dels ocupants, accessibilitat, espais verds, una qualitat mínima de l'edificació i inclusivitat, entre d'altres. | E45: Consulteu els requisits del marc BREEAM
E46: Consulteu els requisits del marc LEED
E47: Consulteu informació sobre GBCE.ES
B48: Medi ambient - circularitat | C48: Totes | D48: Adoptar enfocaments circulars implica reduir la generació de residus, reutilitzar materials i dissenyar productes i processos de manera que en permetin la desmuntabilitat i el reciclatge. Això no només contribueix a disminuir la petjada ambiental, sinó que també comporta beneficis econòmics. Les empreses poden accedir a fonts de materials més sostenibles, reduir costos relacionats amb l'eliminació de residus i enfortir la seva reputació en alinear-se amb pràctiques ambientals avançades. Els clients, per la seva banda, es beneficien de productes més eficients i duradors, alhora que contribueixen a la sostenibilitat ambiental. El Pla d'acció per a l'economia circular de la Unió Europea proporciona directrius i suport per a aquest procés, promou la transició envers pràctiques circulars i crea un entorn propici perquè les empreses prosperin mentre tenen cura del medi ambient. Catalunya Circular és el hub d’innovació i punt de trobada d’empreses i institucions que aporten solucions i estratègies per consolidar l’economia circular a Catalunya. | E48: Consulteu el Pla d'acció per a l'economia circular (UE)
E49: Consulteu l'estàndard Cradle to Cradle
E50: Consulta informació sobre Catalunya Circular, l'Observatori d'economia circular
E51: Consulteu informació sobre l'economia circular (Fundació Ellen McArthur)
B52: Medi ambient - renovables i baixes emissions | C52: Totes | D52: Per al sector de l'edificació, és de vital importància explorar tecnologies que permetin generar energia de manera renovable per satisfer les necessitats dels edificis. Així mateix, s'ha intensificat l'interès en tecnologies de climatització de baixes emissions, com el disseny de sistemes de ventilació natural o la climatització mitjançant l'ús d'aigua subterrània. La implementació d'aquestes mesures pot tenir un impacte significatiu en la reducció de la petjada de carboni dels edificis. | E52: Consulteu informació sobre renovables en edificació
B53: Medi ambient - residus construcció | C53: Totes | D53: El volum de residus de la construcció generats a Catalunya és important tot i que, per les seves característiques, tenen un gran potencial pel que fa a la reutilització i el reciclatge. Aquests residus disposen d’un programa de gestió i d’un model de gestió específics orientats a la prevenció, al reciclatge i a l’impuls dels mercats per a materials reciclats. | E53: Consulteu informació sobre runes, terres i altres residus de la construcció
B54: Medi ambient - Distintiu de garantia de qualitat ambiental | C54: Totes | D54: El Distintiu de garantia de qualitat ambiental és una etiqueta oficial que atorga la Generalitat de Catalunya a productes i serveis que superen determinats requisits de qualitat ambiental més enllà dels establerts com a obligatoris per la normativa vigent. Està dissenyat per ajudar els consumidors a identificar productes i serveis que han estat produïts de manera responsable i sostenible. | E54: Consulteu informació sobre el Distintiu de garantia de qualitat ambiental per a productes de formigó amb material reciclat
E55: Consulteu informació sobre el Distintiu de garantia de qualitat ambiental per a matèries primeres i productes d'àrid reciclat
B56: Social - Codi de bones pràctiques en la promoció i execució d’obres de construcció | C56: Totes | D56: El Codi de Bones Pràctiques en la promoció i execució d'obres de construcció inclou directrius per a la planificació, sostenibilitat, qualitat i gestió de projectes. En relació amb la salut i seguretat, es centra en la prevenció de riscos laborals, la formació dels treballadors i el compliment de la legislació de seguretat en el treball, a fi de garantir un entorn laboral segur en el sector de la construcció. | E56: Consulta informació sobre el Codi de bones pràctiques en la promoció i execució d’obres de construcció
B57: Seguretat i qualitat del producte - Homologació de productes en el sector de la construcció | C57: Totes | D57: L’homologació de productes (prototipus, tipus o models) és un tipus de certificació establerta per una Administració pública que implica el reconeixement oficial que compleixen els requeriments obligatoris definits en especificacions tècniques o normes. Aquesta certificació garanteix que els productes són aptes per a l’ús en la construcció, cosa que contribueix a la seguretat, durabilitat i fiabilitat dels edificis i les estructures. | E57: Consulta informació sobre l'Homologació de Productes en el Sector de la Construcció
B58: Social - Condicions laborals | C58: Totes | D58: El Conveni col·lectiu del sector de la construcció i obres públiques i materials de la construcció és un acord laboral que estableix les condicions de treball per als empleats d’aquest sector. | E58: Consulta informació sobre el Conveni Col·lectiu del sector de la construcció i obres públiques i materials de la construcció
B59: Estratègia catalana per a la renovació energètica d'edificis | C59: Totes | D59: Aquesta Estratègia, aprovada pel Govern, busca promoure la renovació energètica dels edificis i pot influir en el sector de la construcció en termes de sostenibilitat i eficiència energètica, aspectes clau per al bon govern en aquest sector. | E59: Consulta informació sobre l'Estratègia Catalana per a la Renovació Energètica d'Edificis
B60: Bon govern - Competència responsable | C60: Totes | D60: La societat pública Infraestructures de la Generalitat de Catalunya, SAU, gestiona el procés de licitació i execució d’obres d’actuacions de construcció, conservació, manteniment i modernització d’edificacions i infraestructures per encàrrec de l’Administració de la Generalitat o del seu sector públic. Això inclou la gestió de contractes, la supervisió de l’execució i el desenvolupament d’estudis i projectes. | E60: Consulta informació sobre les Infraestructures de la Generalitat de Catalunya, SAU
B61: Bon govern - Control de qualitat de l'edificació | C61: Totes | D61: Informació proporcionada per la Generalitat de Catalunya sobre els instruments de control de la qualitat de l'edificació | E61: Consulta informació sobre el Control de qualitat de l'edificació

Sheet Arquitectura i Enginyeria
D1: Serveis tècnics d'arquitectura i enginyeria | E1: Aquest sector representa el CNAE 71, específicament dedicat als serveis tècnics d'arquitectura i enginyeria.
D3: Oportunitats de construcció sostenible | E3: Biodiversitat i ecosistemes | F3: Eficiència energètica i energies renovables | G3: Disseny del producte i gestió del cicle de vida | H3: Gestió sostenible de l'aigua | I3: Seguretat química
